Workbook

Sheet CAPA
B2: Comparador de Fundos
B4: Fundos D+1
B5: Nome | C5: CNPJ | D5: Classificação | E5: Gestora | F5: Administradora | G5: Taxa de Adm. | H5: 46113 | I5: Acumulado | J5: Volatilidade | K5: PL Atual | L5: Início do Fundo
A6: 216658 | B6: GERAES | C6: 09.720.734/0001-10 | D6: =INDEX(Planilha2!$E:$E,MATCH(CAPA!A6,Planilha2!$D:$D,0)) -> Renda Fixa Duração Livre Grau de Investimento | E6: =INDEX(Planilha2!$F:$F,MATCH(CAPA!A6,Planilha2!$D:$D,0)) -> Af Invest Administração de Recursos Ltda | F6: =INDEX(Planilha2!$G:$G,MATCH(CAPA!A6,Planilha2!$D:$D,0)) -> BTG Pactual Servicos Financeiros S/A Dtv | G6: =INDEX(Planilha2!$H:$H,MATCH(CAPA!A6,Planilha2!$D:$D,0)) -> 0 | H6: =(_xlfn.XLOOKUP(A6,Cotas!$C$1:$C$27,Cotas!$E$1:$E$27)/_xlfn.XLOOKUP(A6,Cotas!$C$1:$C$27,Cotas!$F$1:$F$27))-1 -> 0.010127895 | I6: =(INDEX(Planilha2!$J:$J,MATCH(A6,Planilha2!$D:$D,0)))/Cotas!G11-1 -> 4.4968332 | J6: =INDEX(Planilha2!$L:$L,MATCH(CAPA!A6,Planilha2!$D:$D,0)) -> 0.63200306 | K6: =INDEX(Planilha2!$M:$M,MATCH(CAPA!A6,Planilha2!$D:$D,0)) -> 539746.11 | L6: =INDEX(Planilha2!$K:$K,MATCH(CAPA!A6,Planilha2!$D:$D,0)) -> 39702
A7: 634468 | B7: ARX Denali | C7: 41.888.219/0001-56 | D7: =INDEX(Planilha2!$E:$E,MATCH(CAPA!A7,Planilha2!$D:$D,0)) -> Renda Fixa Duração Baixa Grau de Investimento | E7: =INDEX(Planilha2!$F:$F,MATCH(CAPA!A7,Planilha2!$D:$D,0)) -> ARX Investimentos Ltda. | F7: =INDEX(Planilha2!$G:$G,MATCH(CAPA!A7,Planilha2!$D:$D,0)) -> BNY Mellon Serviços Financeiros Dtvm S/A | G7: =INDEX(Planilha2!$H:$H,MATCH(CAPA!A7,Planilha2!$D:$D,0)) -> 0 | H7: =(_xlfn.XLOOKUP(A7,Cotas!$C$1:$C$27,Cotas!$E$1:$E$27)/_xlfn.XLOOKUP(A7,Cotas!$C$1:$C$27,Cotas!$F$1:$F$27))-1 -> 0.011376612 | I7: =(INDEX(Planilha2!$J:$J,MATCH(A7,Planilha2!$D:$D,0)))/Cotas!H2-1 -> 0.7662261 | J7: =INDEX(Planilha2!$L:$L,MATCH(CAPA!A7,Planilha2!$D:$D,0)) -> 0.370749 | K7: =INDEX(Planilha2!$M:$M,MATCH(CAPA!A7,Planilha2!$D:$D,0)) -> 1598464.3 | L7: =INDEX(Planilha2!$K:$K,MATCH(CAPA!A7,Planilha2!$D:$D,0)) -> 44413
A8: 284491 | B8: Capitânia Top | C8: 13.615.411/0001-33 | D8: =INDEX(Planilha2!$E:$E,MATCH(CAPA!A8,Planilha2!$D:$D,0)) -> Renda Fixa Duração Média Crédito Livre | E8: =INDEX(Planilha2!$F:$F,MATCH(CAPA!A8,Planilha2!$D:$D,0)) -> Capitania Capital | F8: =INDEX(Planilha2!$G:$G,MATCH(CAPA!A8,Planilha2!$D:$D,0)) -> BNY Mellon Serviços Financeiros Dtvm S/A | G8: =INDEX(Planilha2!$H:$H,MATCH(CAPA!A8,Planilha2!$D:$D,0)) -> 0 | H8: =(_xlfn.XLOOKUP(A8,Cotas!$C$1:$C$27,Cotas!$E$1:$E$27)/_xlfn.XLOOKUP(A8,Cotas!$C$1:$C$27,Cotas!$F$1:$F$27))-1 -> 0.013949155 | I8: =(INDEX(Planilha2!$J:$J,MATCH(A8,Planilha2!$D:$D,0)))/Cotas!I5-1 -> 2.8310575 | J8: =INDEX(Planilha2!$L:$L,MATCH(CAPA!A8,Planilha2!$D:$D,0)) -> 0.88878195 | K8: =INDEX(Planilha2!$M:$M,MATCH(CAPA!A8,Planilha2!$D:$D,0)) -> 203260.47 | L8: =INDEX(Planilha2!$K:$K,MATCH(CAPA!A8,Planilha2!$D:$D,0)) -> 39589
A9: 531553 | B9: Riza Lotus | C9: 36.498.670/0001-27 | D9: =INDEX(Planilha2!$E:$E,MATCH(CAPA!A9,Planilha2!$D:$D,0)) -> Renda Fixa Duração Livre Grau de Investimento | E9: =INDEX(Planilha2!$F:$F,MATCH(CAPA!A9,Planilha2!$D:$D,0)) -> Riza Líquidos | F9: =INDEX(Planilha2!$G:$G,MATCH(CAPA!A9,Planilha2!$D:$D,0)) -> BTG Pactual Servicos Financeiros S/A Dtv | G9: =INDEX(Planilha2!$H:$H,MATCH(CAPA!A9,Planilha2!$D:$D,0)) -> 0.4 | H9: =(_xlfn.XLOOKUP(A9,Cotas!$C$1:$C$27,Cotas!$E$1:$E$27)/_xlfn.XLOOKUP(A9,Cotas!$C$1:$C$27,Cotas!$F$1:$F$27))-1 -> 0.010575743 | I9: =(INDEX(Planilha2!$J:$J,MATCH(A9,Planilha2!$D:$D,0)))/Cotas!J12-1 -> 0.9132096 | J9: =INDEX(Planilha2!$L:$L,MATCH(CAPA!A9,Planilha2!$D:$D,0)) -> 0.33481661 | K9: =INDEX(Planilha2!$M:$M,MATCH(CAPA!A9,Planilha2!$D:$D,0)) -> 3801596.9 | L9: =INDEX(Planilha2!$K:$K,MATCH(CAPA!A9,Planilha2!$D:$D,0)) -> 43907
A10: 489956 | B10: Western Asset Total | C10: 28.320.756/0001-37 | D10: =INDEX(Planilha2!$E:$E,MATCH(CAPA!A10,Planilha2!$D:$D,0)) -> Renda Fixa Duração Baixa Grau de Investimento | E10: =INDEX(Planilha2!$F:$F,MATCH(CAPA!A10,Planilha2!$D:$D,0)) -> Franklin Templeton Brasil Ltda | F10: =INDEX(Planilha2!$G:$G,MATCH(CAPA!A10,Planilha2!$D:$D,0)) -> Banco BNP Paribas Brasil S/A | G10: =INDEX(Planilha2!$H:$H,MATCH(CAPA!A10,Planilha2!$D:$D,0)) -> 0 | H10: =(_xlfn.XLOOKUP(A10,Cotas!$C$1:$C$27,Cotas!$E$1:$E$27)/_xlfn.XLOOKUP(A10,Cotas!$C$1:$C$27,Cotas!$F$1:$F$27))-1 -> 0.010682849 | I10: =(INDEX(Planilha2!$J:$J,MATCH(A10,Planilha2!$D:$D,0)))/Cotas!K14-1 -> 0.92662118 | J10: =INDEX(Planilha2!$L:$L,MATCH(CAPA!A10,Planilha2!$D:$D,0)) -> 0.78192199 | K10: =INDEX(Planilha2!$M:$M,MATCH(CAPA!A10,Planilha2!$D:$D,0)) -> 3569168.5 | L10: =INDEX(Planilha2!$K:$K,MATCH(CAPA!A10,Planilha2!$D:$D,0)) -> 43538
A11: 259624 | B11: Daycoval Classic | C11: 10.783.480/0001-68 | D11: =INDEX(Planilha2!$E:$E,MATCH(CAPA!A11,Planilha2!$D:$D,0)) -> Renda Fixa Duração Baixa Grau de Investimento | E11: =INDEX(Planilha2!$F:$F,MATCH(CAPA!A11,Planilha2!$D:$D,0)) -> Daycoval Asset Manag | F11: =INDEX(Planilha2!$G:$G,MATCH(CAPA!A11,Planilha2!$D:$D,0)) -> Banco Daycoval S.A. | G11: =INDEX(Planilha2!$H:$H,MATCH(CAPA!A11,Planilha2!$D:$D,0)) -> 0 | H11: =(_xlfn.XLOOKUP(A11,Cotas!$C$1:$C$27,Cotas!$E$1:$E$27)/_xlfn.XLOOKUP(A11,Cotas!$C$1:$C$27,Cotas!$F$1:$F$27))-1 -> 0.010100012 | I11: =(INDEX(Planilha2!$J:$J,MATCH(A11,Planilha2!$D:$D,0)))/Cotas!L16-1 -> 3.7860695 | J11: =INDEX(Planilha2!$L:$L,MATCH(CAPA!A11,Planilha2!$D:$D,0)) -> 0.38517713 | K11: =INDEX(Planilha2!$M:$M,MATCH(CAPA!A11,Planilha2!$D:$D,0)) -> 2164491.5 | L11: =INDEX(Planilha2!$K:$K,MATCH(CAPA!A11,Planilha2!$D:$D,0)) -> 40389
A12: 456497 | B12: Iridium Apollo | C12: 26.978.438/0001-32 | D12: =INDEX(Planilha2!$E:$E,MATCH(CAPA!A12,Planilha2!$D:$D,0)) -> Renda Fixa Duração Livre Grau de Investimento | E12: =INDEX(Planilha2!$F:$F,MATCH(CAPA!A12,Planilha2!$D:$D,0)) -> Iridium Gestão de Recursos Ltda. | F12: =INDEX(Planilha2!$G:$G,MATCH(CAPA!A12,Planilha2!$D:$D,0)) -> BNY Mellon Serviços Financeiros Dtvm S/A | G12: =INDEX(Planilha2!$H:$H,MATCH(CAPA!A12,Planilha2!$D:$D,0)) -> 0 | H12: =(_xlfn.XLOOKUP(A12,Cotas!$C$1:$C$27,Cotas!$E$1:$E$27)/_xlfn.XLOOKUP(A12,Cotas!$C$1:$C$27,Cotas!$F$1:$F$27))-1 -> 0.011990377 | I12: =(INDEX(Planilha2!$J:$J,MATCH(A12,Planilha2!$D:$D,0)))/Cotas!M18-1 -> 1.0870277 | J12: =INDEX(Planilha2!$L:$L,MATCH(CAPA!A12,Planilha2!$D:$D,0)) -> 0.88568006 | K12: =INDEX(Planilha2!$M:$M,MATCH(CAPA!A12,Planilha2!$D:$D,0)) -> 1387027 | L12: =INDEX(Planilha2!$K:$K,MATCH(CAPA!A12,Planilha2!$D:$D,0)) -> 43047
A13: 361445 | B13: Porto Seguro FIRF | C13: 18.719.154/0001-01 | D13: =INDEX(Planilha2!$E:$E,MATCH(CAPA!A13,Planilha2!$D:$D,0)) -> Renda Fixa Duração Baixa Grau de Investimento | E13: =INDEX(Planilha2!$F:$F,MATCH(CAPA!A13,Planilha2!$D:$D,0)) -> Porto Seguro Investimentos Ltda. | F13: =INDEX(Planilha2!$G:$G,MATCH(CAPA!A13,Planilha2!$D:$D,0)) -> Intrag Dist. de Títu | G13: =INDEX(Planilha2!$H:$H,MATCH(CAPA!A13,Planilha2!$D:$D,0)) -> 0 | H13: =(_xlfn.XLOOKUP(A13,Cotas!$C$1:$C$27,Cotas!$E$1:$E$27)/_xlfn.XLOOKUP(A13,Cotas!$C$1:$C$27,Cotas!$F$1:$F$27))-1 -> 0.010954673 | I13: =(INDEX(Planilha2!$J:$J,MATCH(A13,Planilha2!$D:$D,0)))/Cotas!N24-1 -> 2.3245078 | J13: =INDEX(Planilha2!$L:$L,MATCH(CAPA!A13,Planilha2!$D:$D,0)) -> 0.54447902 | K13: =INDEX(Planilha2!$M:$M,MATCH(CAPA!A13,Planilha2!$D:$D,0)) -> 6892815.2 | L13: =INDEX(Planilha2!$K:$K,MATCH(CAPA!A13,Planilha2!$D:$D,0)) -> 41698
A14: 635091 | B14: Nu Reserva Imediata | C14: 42.699.466/0001-77 | D14: =INDEX(Planilha2!$E:$E,MATCH(CAPA!A14,Planilha2!$D:$D,0)) -> Renda Fixa Duração Baixa Grau de Investimento | E14: =INDEX(Planilha2!$F:$F,MATCH(CAPA!A14,Planilha2!$D:$D,0)) -> Nu Asset Management Ltda. | F14: =INDEX(Planilha2!$G:$G,MATCH(CAPA!A14,Planilha2!$D:$D,0)) -> Intrag Dist. de Títu | G14: =INDEX(Planilha2!$H:$H,MATCH(CAPA!A14,Planilha2!$D:$D,0)) -> 0 | H14: =(_xlfn.XLOOKUP(A14,Cotas!$C$1:$C$27,Cotas!$E$1:$E$27)/_xlfn.XLOOKUP(A14,Cotas!$C$1:$C$27,Cotas!$F$1:$F$27))-1 -> 0.0099662639 | I14: =(INDEX(Planilha2!$J:$J,MATCH(A14,Planilha2!$D:$D,0)))/1-1 -> 0.6933984 | J14: =INDEX(Planilha2!$L:$L,MATCH(CAPA!A14,Planilha2!$D:$D,0)) -> 0.44668576 | K14: =INDEX(Planilha2!$M:$M,MATCH(CAPA!A14,Planilha2!$D:$D,0)) -> 2834785.7 | L14: =INDEX(Planilha2!$K:$K,MATCH(CAPA!A14,Planilha2!$D:$D,0)) -> 44574
A15: 387444 | B15: Inter Conservador | C15: 20.879.578/0001-77 | D15: =INDEX(Planilha2!$E:$E,MATCH(CAPA!A15,Planilha2!$D:$D,0)) -> Renda Fixa Duração Baixa Grau de Investimento | E15: =INDEX(Planilha2!$F:$F,MATCH(CAPA!A15,Planilha2!$D:$D,0)) -> Inter Asset | F15: =INDEX(Planilha2!$G:$G,MATCH(CAPA!A15,Planilha2!$D:$D,0)) -> Inter Distribuidora de Títulos e Valores | G15: =INDEX(Planilha2!$H:$H,MATCH(CAPA!A15,Planilha2!$D:$D,0)) -> 0 | H15: =(_xlfn.XLOOKUP(A15,Cotas!$C$1:$C$27,Cotas!$E$1:$E$27)/_xlfn.XLOOKUP(A15,Cotas!$C$1:$C$27,Cotas!$F$1:$F$27))-1 -> 0.011140631 | I15: =(INDEX(Planilha2!$J:$J,MATCH(A15,Planilha2!$D:$D,0)))/1-1 -> 1.9001288 | J15: =INDEX(Planilha2!$L:$L,MATCH(CAPA!A15,Planilha2!$D:$D,0)) -> 0.82942731 | K15: =INDEX(Planilha2!$M:$M,MATCH(CAPA!A15,Planilha2!$D:$D,0)) -> 1344300.3 | L15: =INDEX(Planilha2!$K:$K,MATCH(CAPA!A15,Planilha2!$D:$D,0)) -> 42034
A16: 677930 | B16: Absolute Atenas | C16: 48.096.589/0001-08 | D16: =INDEX(Planilha2!$E:$E,MATCH(CAPA!A16,Planilha2!$D:$D,0)) -> Renda Fixa Duração Baixa Grau de Investimento | E16: =INDEX(Planilha2!$F:$F,MATCH(CAPA!A16,Planilha2!$D:$D,0)) -> Absolute Crédito | F16: =INDEX(Planilha2!$G:$G,MATCH(CAPA!A16,Planilha2!$D:$D,0)) -> BTG Pactual Servicos Financeiros S/A Dtv | G16: =INDEX(Planilha2!$H:$H,MATCH(CAPA!A16,Planilha2!$D:$D,0)) -> 0 | H16: =(_xlfn.XLOOKUP(A16,Cotas!$C$1:$C$27,Cotas!$E$1:$E$27)/_xlfn.XLOOKUP(A16,Cotas!$C$1:$C$27,Cotas!$F$1:$F$27))-1 -> 0.0099284703 | I16: =(INDEX(Planilha2!$J:$J,MATCH(A16,Planilha2!$D:$D,0)))/1-1 -> 0.56863965 | J16: =INDEX(Planilha2!$L:$L,MATCH(CAPA!A16,Planilha2!$D:$D,0)) -> 0.26345109 | K16: =INDEX(Planilha2!$M:$M,MATCH(CAPA!A16,Planilha2!$D:$D,0)) -> 734275.08 | L16: =INDEX(Planilha2!$K:$K,MATCH(CAPA!A16,Planilha2!$D:$D,0)) -> 44862
B20: Fundos D+30
B21: Nome | C21: CNPJ | D21: Classificação | E21: Gestora | F21: Administradora | G21: Taxa de Adm. | H21: 46113 | I21: Acumulado | J21: Volatilidade | K21: PL Atual | L21: Início do Fundo
A22: 462276 | B22: Geraes 30 | C22: 29.044.189/0001-04 | D22: =INDEX(Planilha2!$E:$E,MATCH(CAPA!A22,Planilha2!$D:$D,0)) -> Renda Fixa Duração Livre Grau de Investimento | E22: =INDEX(Planilha2!$F:$F,MATCH(CAPA!A22,Planilha2!$D:$D,0)) -> Af Invest Administração de Recursos Ltda | F22: =INDEX(Planilha2!$G:$G,MATCH(CAPA!A22,Planilha2!$D:$D,0)) -> BTG Pactual Servicos Financeiros S/A Dtv | G22: =INDEX(Planilha2!$H:$H,MATCH(CAPA!A22,Planilha2!$D:$D,0)) -> 0 | H22: =(_xlfn.XLOOKUP(A22,Cotas!$C$1:$C$27,Cotas!$E$1:$E$27)/_xlfn.XLOOKUP(A22,Cotas!$C$1:$C$27,Cotas!$F$1:$F$27))-1 -> 0.0094101092 | I22: =(INDEX(Planilha2!$J:$J,MATCH(A22,Planilha2!$D:$D,0)))/1-1 -> 1.0633091 | J22: =INDEX(Planilha2!$L:$L,MATCH(CAPA!A22,Planilha2!$D:$D,0)) -> 1.101544 | K22: =INDEX(Planilha2!$M:$M,MATCH(CAPA!A22,Planilha2!$D:$D,0)) -> 311423.16 | L22: =INDEX(Planilha2!$K:$K,MATCH(CAPA!A22,Planilha2!$D:$D,0)) -> 43187
A23: 470473 | B23: Daycoval Classic 30 | C23: 29.250.121/0001-73 | D23: =INDEX(Planilha2!$E:$E,MATCH(CAPA!A23,Planilha2!$D:$D,0)) -> Renda Fixa Duração Baixa Grau de Investimento | E23: =INDEX(Planilha2!$F:$F,MATCH(CAPA!A23,Planilha2!$D:$D,0)) -> Daycoval Asset Manag | F23: =INDEX(Planilha2!$G:$G,MATCH(CAPA!A23,Planilha2!$D:$D,0)) -> Banco Daycoval S.A. | G23: =INDEX(Planilha2!$H:$H,MATCH(CAPA!A23,Planilha2!$D:$D,0)) -> 0 | H23: =(_xlfn.XLOOKUP(A23,Cotas!$C$1:$C$27,Cotas!$E$1:$E$27)/_xlfn.XLOOKUP(A23,Cotas!$C$1:$C$27,Cotas!$F$1:$F$27))-1 -> 0.010964912 | I23: =(INDEX(Planilha2!$J:$J,MATCH(A23,Planilha2!$D:$D,0)))/1-1 -> 1.1051864 | J23: =INDEX(Planilha2!$L:$L,MATCH(CAPA!A23,Planilha2!$D:$D,0)) -> 0.60675787 | K23: =INDEX(Planilha2!$M:$M,MATCH(CAPA!A23,Planilha2!$D:$D,0)) -> 865976.73 | L23: =INDEX(Planilha2!$K:$K,MATCH(CAPA!A23,Planilha2!$D:$D,0)) -> 43283
A24: 620955 | B24: Riza Lotus Plus | C24: 43.917.493/0001-31 | D24: =INDEX(Planilha2!$E:$E,MATCH(CAPA!A24,Planilha2!$D:$D,0)) -> Renda Fixa Duração Livre Grau de Investimento | E24: =INDEX(Planilha2!$F:$F,MATCH(CAPA!A24,Planilha2!$D:$D,0)) -> Riza Líquidos | F24: =INDEX(Planilha2!$G:$G,MATCH(CAPA!A24,Planilha2!$D:$D,0)) -> BTG Pactual Servicos Financeiros S/A Dtv | G24: =INDEX(Planilha2!$H:$H,MATCH(CAPA!A24,Planilha2!$D:$D,0)) -> 0 | H24: =(_xlfn.XLOOKUP(A24,Cotas!$C$1:$C$27,Cotas!$E$1:$E$27)/_xlfn.XLOOKUP(A24,Cotas!$C$1:$C$27,Cotas!$F$1:$F$27))-1 -> 0.010181018 | I24: =(INDEX(Planilha2!$J:$J,MATCH(A24,Planilha2!$D:$D,0)))/1-1 -> 0.7399199 | J24: =INDEX(Planilha2!$L:$L,MATCH(CAPA!A24,Planilha2!$D:$D,0)) -> 0.89491432 | K24: =INDEX(Planilha2!$M:$M,MATCH(CAPA!A24,Planilha2!$D:$D,0)) -> 498517.97 | L24: =INDEX(Planilha2!$K:$K,MATCH(CAPA!A24,Planilha2!$D:$D,0)) -> 44498
A25: 601462 | B25: ARX Vinson Advisory | C25: 41.888.492/0001-80 | D25: =INDEX(Planilha2!$E:$E,MATCH(CAPA!A25,Planilha2!$D:$D,0)) -> Renda Fixa Duração Baixa Grau de Investimento | E25: =INDEX(Planilha2!$F:$F,MATCH(CAPA!A25,Planilha2!$D:$D,0)) -> ARX Investimentos Ltda. | F25: =INDEX(Planilha2!$G:$G,MATCH(CAPA!A25,Planilha2!$D:$D,0)) -> BNY Mellon Serviços Financeiros Dtvm S/A | G25: =INDEX(Planilha2!$H:$H,MATCH(CAPA!A25,Planilha2!$D:$D,0)) -> 0 | H25: =(_xlfn.XLOOKUP(A25,Cotas!$C$1:$C$27,Cotas!$E$1:$E$27)/_xlfn.XLOOKUP(A25,Cotas!$C$1:$C$27,Cotas!$F$1:$F$27))-1 -> 0.011915693 | I25: =(INDEX(Planilha2!$J:$J,MATCH(A25,Planilha2!$D:$D,0)))/1-1 -> 0.7933704 | J25: =INDEX(Planilha2!$L:$L,MATCH(CAPA!A25,Planilha2!$D:$D,0)) -> 0.52976793 | K25: =INDEX(Planilha2!$M:$M,MATCH(CAPA!A25,Planilha2!$D:$D,0)) -> 1251713.9 | L25: =INDEX(Planilha2!$K:$K,MATCH(CAPA!A25,Planilha2!$D:$D,0)) -> 44393
A26: 493831 | B26: Sparta Max Advisory | C26: 32.757.330/0001-12 | D26: =INDEX(Planilha2!$E:$E,MATCH(CAPA!A26,Planilha2!$D:$D,0)) -> Renda Fixa Duração Média Crédito Livre | E26: =INDEX(Planilha2!$F:$F,MATCH(CAPA!A26,Planilha2!$D:$D,0)) -> Sparta Administradora de Recursos Ltda | F26: =INDEX(Planilha2!$G:$G,MATCH(CAPA!A26,Planilha2!$D:$D,0)) -> BNY Mellon Serviços Financeiros Dtvm S/A | G26: =INDEX(Planilha2!$H:$H,MATCH(CAPA!A26,Planilha2!$D:$D,0)) -> 0 | H26: =(_xlfn.XLOOKUP(A26,Cotas!$C$1:$C$27,Cotas!$E$1:$E$27)/_xlfn.XLOOKUP(A26,Cotas!$C$1:$C$27,Cotas!$F$1:$F$27))-1 -> 0.011867118 | I26: =(INDEX(Planilha2!$J:$J,MATCH(A26,Planilha2!$D:$D,0)))/1-1 -> 1.034299 | J26: =INDEX(Planilha2!$L:$L,MATCH(CAPA!A26,Planilha2!$D:$D,0)) -> 0.85969764 | K26: =INDEX(Planilha2!$M:$M,MATCH(CAPA!A26,Planilha2!$D:$D,0)) -> 140665.95 | L26: =INDEX(Planilha2!$K:$K,MATCH(CAPA!A26,Planilha2!$D:$D,0)) -> 43585
A27: 478008 | B27: Polo Crédito Corporativo | C27: 31.455.879/0001-90 | D27: =INDEX(Planilha2!$E:$E,MATCH(CAPA!A27,Planilha2!$D:$D,0)) -> Renda Fixa Duração Livre Crédito Livre | E27: =INDEX(Planilha2!$F:$F,MATCH(CAPA!A27,Planilha2!$D:$D,0)) -> Polo Capital Gestão de Recurso | F27: =INDEX(Planilha2!$G:$G,MATCH(CAPA!A27,Planilha2!$D:$D,0)) -> BNY Mellon Serviços Financeiros Dtvm S/A | G27: =INDEX(Planilha2!$H:$H,MATCH(CAPA!A27,Planilha2!$D:$D,0)) -> 0 | H27: =(_xlfn.XLOOKUP(A27,Cotas!$C$1:$C$27,Cotas!$E$1:$E$27)/_xlfn.XLOOKUP(A27,Cotas!$C$1:$C$27,Cotas!$F$1:$F$27))-1 -> 0.0082275174 | I27: =(INDEX(Planilha2!$J:$J,MATCH(A27,Planilha2!$D:$D,0)))/1-1 -> 1.1123136 | J27: =INDEX(Planilha2!$L:$L,MATCH(CAPA!A27,Planilha2!$D:$D,0)) -> 0.6130043 | K27: =INDEX(Planilha2!$M:$M,MATCH(CAPA!A27,Planilha2!$D:$D,0)) -> 1157810.9 | L27: =INDEX(Planilha2!$K:$K,MATCH(CAPA!A27,Planilha2!$D:$D,0)) -> 43395
A28: 494607 | B28: Iridium Titan Advisory | C28: 32.756.812/0001-58 | D28: =INDEX(Planilha2!$E:$E,MATCH(CAPA!A28,Planilha2!$D:$D,0)) -> Renda Fixa Duração Livre Crédito Livre | E28: =INDEX(Planilha2!$F:$F,MATCH(CAPA!A28,Planilha2!$D:$D,0)) -> Iridium Gestão de Recursos Ltda. | F28: =INDEX(Planilha2!$G:$G,MATCH(CAPA!A28,Planilha2!$D:$D,0)) -> BNY Mellon Serviços Financeiros Dtvm S/A | G28: =INDEX(Planilha2!$H:$H,MATCH(CAPA!A28,Planilha2!$D:$D,0)) -> 0 | H28: =(_xlfn.XLOOKUP(A28,Cotas!$C$1:$C$27,Cotas!$E$1:$E$27)/_xlfn.XLOOKUP(A28,Cotas!$C$1:$C$27,Cotas!$F$1:$F$27))-1 -> 0.012573542 | I28: =(INDEX(Planilha2!$J:$J,MATCH(A28,Planilha2!$D:$D,0)))/1-1 -> 1.0185206 | J28: =INDEX(Planilha2!$L:$L,MATCH(CAPA!A28,Planilha2!$D:$D,0)) -> 0.67011672 | K28: =INDEX(Planilha2!$M:$M,MATCH(CAPA!A28,Planilha2!$D:$D,0)) -> 187499.27 | L28: =INDEX(Planilha2!$K:$K,MATCH(CAPA!A28,Planilha2!$D:$D,0)) -> 43591
A29: 523666 | B29: Porto Seguro Ipê | C29: 35.378.376/0001-19 | D29: =INDEX(Planilha2!$E:$E,MATCH(CAPA!A29,Planilha2!$D:$D,0)) -> Renda Fixa Duração Livre Crédito Livre | E29: =INDEX(Planilha2!$F:$F,MATCH(CAPA!A29,Planilha2!$D:$D,0)) -> Porto Seguro Investimentos Ltda. | F29: =INDEX(Planilha2!$G:$G,MATCH(CAPA!A29,Planilha2!$D:$D,0)) -> Intrag Dist. de Títu | G29: =INDEX(Planilha2!$H:$H,MATCH(CAPA!A29,Planilha2!$D:$D,0)) -> 0 | H29: =(_xlfn.XLOOKUP(A29,Cotas!$C$1:$C$27,Cotas!$E$1:$E$27)/_xlfn.XLOOKUP(A29,Cotas!$C$1:$C$27,Cotas!$F$1:$F$27))-1 -> 0.011851861 | I29: =(INDEX(Planilha2!$J:$J,MATCH(A29,Planilha2!$D:$D,0)))/100-1 -> 0.94542516 | J29: =INDEX(Planilha2!$L:$L,MATCH(CAPA!A29,Planilha2!$D:$D,0)) -> 0.70542075 | K29: =INDEX(Planilha2!$M:$M,MATCH(CAPA!A29,Planilha2!$D:$D,0)) -> 535325.15 | L29: =INDEX(Planilha2!$K:$K,MATCH(CAPA!A29,Planilha2!$D:$D,0)) -> 43798
A30: 494089 | B30: Sparta Top Advisory | C30: 32.846.811/0001-02 | D30: =INDEX(Planilha2!$E:$E,MATCH(CAPA!A30,Planilha2!$D:$D,0)) -> Renda Fixa Duração Média Grau de Investimento | E30: =INDEX(Planilha2!$F:$F,MATCH(CAPA!A30,Planilha2!$D:$D,0)) -> Sparta Administradora de Recursos Ltda | F30: =INDEX(Planilha2!$G:$G,MATCH(CAPA!A30,Planilha2!$D:$D,0)) -> BNY Mellon Serviços Financeiros Dtvm S/A | G30: =INDEX(Planilha2!$H:$H,MATCH(CAPA!A30,Planilha2!$D:$D,0)) -> 0 | H30: =(_xlfn.XLOOKUP(A30,Cotas!$C$1:$C$27,Cotas!$E$1:$E$27)/_xlfn.XLOOKUP(A30,Cotas!$C$1:$C$27,Cotas!$F$1:$F$27))-1 -> 0.010831797 | I30: =(INDEX(Planilha2!$J:$J,MATCH(A30,Planilha2!$D:$D,0)))/1-1 -> 0.94383778 | J30: =INDEX(Planilha2!$L:$L,MATCH(CAPA!A30,Planilha2!$D:$D,0)) -> 0.83844845 | K30: =INDEX(Planilha2!$M:$M,MATCH(CAPA!A30,Planilha2!$D:$D,0)) -> 574548.93 | L30: =INDEX(Planilha2!$K:$K,MATCH(CAPA!A30,Planilha2!$D:$D,0)) -> 43579
A31: 678007 | B31: Absolute Creta | C31: 48.122.126/0001-65 | D31: =INDEX(Planilha2!$E:$E,MATCH(CAPA!A31,Planilha2!$D:$D,0)) -> Renda Fixa Duração Baixa Grau de Investimento | E31: =INDEX(Planilha2!$F:$F,MATCH(CAPA!A31,Planilha2!$D:$D,0)) -> Absolute Crédito | F31: =INDEX(Planilha2!$G:$G,MATCH(CAPA!A31,Planilha2!$D:$D,0)) -> BTG Pactual Servicos Financeiros S/A Dtv | G31: =INDEX(Planilha2!$H:$H,MATCH(CAPA!A31,Planilha2!$D:$D,0)) -> 0 | H31: =(_xlfn.XLOOKUP(A31,Cotas!$C$1:$C$27,Cotas!$E$1:$E$27)/_xlfn.XLOOKUP(A31,Cotas!$C$1:$C$27,Cotas!$F$1:$F$27))-1 -> 0.0083405799 | I31: =(INDEX(Planilha2!$J:$J,MATCH(A31,Planilha2!$D:$D,0)))/1-1 -> 0.58598776 | J31: =INDEX(Planilha2!$L:$L,MATCH(CAPA!A31,Planilha2!$D:$D,0)) -> 0.4832305 | K31: =INDEX(Planilha2!$M:$M,MATCH(CAPA!A31,Planilha2!$D:$D,0)) -> 1721026.5 | L31: =INDEX(Planilha2!$K:$K,MATCH(CAPA!A31,Planilha2!$D:$D,0)) -> 44862
B35: Fundos D+60
B36: Nome | C36: CNPJ | D36: Classificação | E36: Gestora | F36: Administradora | G36: Taxa de Adm. | H36: 46113 | I36: Acumulado | J36: Volatilidade | K36: PL Atual | L36: Início do Fundo
A37: 624977 | B37: Horizonte | C37: 44.025.131/0001-07 | D37: =INDEX(Planilha2!$E:$E,MATCH(CAPA!A37,Planilha2!$D:$D,0)) -> Multimercados Livre | E37: =INDEX(Planilha2!$F:$F,MATCH(CAPA!A37,Planilha2!$D:$D,0)) -> Af Invest Administração de Recursos Ltda | F37: =INDEX(Planilha2!$G:$G,MATCH(CAPA!A37,Planilha2!$D:$D,0)) -> BTG Pactual Servicos Financeiros S/A Dtv | G37: =INDEX(Planilha2!$H:$H,MATCH(CAPA!A37,Planilha2!$D:$D,0)) -> 0 | H37: =(_xlfn.XLOOKUP(A37,Cotas!$C$1:$C$27,Cotas!$E$1:$E$27)/_xlfn.XLOOKUP(A37,Cotas!$C$1:$C$27,Cotas!$F$1:$F$27))-1 -> 0.01076937 | I37: =(INDEX(Planilha2!$J:$J,MATCH(A37,Planilha2!$D:$D,0)))/1-1 -> 0.7252344 | J37: =INDEX(Planilha2!$L:$L,MATCH(CAPA!A37,Planilha2!$D:$D,0)) -> 0.91291145 | K37: =INDEX(Planilha2!$M:$M,MATCH(CAPA!A37,Planilha2!$D:$D,0)) -> 230557.05 | L37: =INDEX(Planilha2!$K:$K,MATCH(CAPA!A37,Planilha2!$D:$D,0)) -> 44523
A38: 393185 | B38: JGP Select | C38: 21.946.695/0001-79 | D38: =INDEX(Planilha2!$E:$E,MATCH(CAPA!A38,Planilha2!$D:$D,0)) -> Multimercados Estratégia Específica | E38: =INDEX(Planilha2!$F:$F,MATCH(CAPA!A38,Planilha2!$D:$D,0)) -> Jgp Gestão de Crédito Ltda. | F38: =INDEX(Planilha2!$G:$G,MATCH(CAPA!A38,Planilha2!$D:$D,0)) -> BNY Mellon Serviços Financeiros Dtvm S/A | G38: =INDEX(Planilha2!$H:$H,MATCH(CAPA!A38,Planilha2!$D:$D,0)) -> 0 | H38: =(_xlfn.XLOOKUP(A38,Cotas!$C$1:$C$27,Cotas!$E$1:$E$27)/_xlfn.XLOOKUP(A38,Cotas!$C$1:$C$27,Cotas!$F$1:$F$27))-1 -> 0.010999159 | I38: =(INDEX(Planilha2!$J:$J,MATCH(A38,Planilha2!$D:$D,0)))/100-1 -> 2.2129301 | J38: =INDEX(Planilha2!$L:$L,MATCH(CAPA!A38,Planilha2!$D:$D,0)) -> 1.5295323 | K38: =INDEX(Planilha2!$M:$M,MATCH(CAPA!A38,Planilha2!$D:$D,0)) -> 347114.09 | L38: =INDEX(Planilha2!$K:$K,MATCH(CAPA!A38,Planilha2!$D:$D,0)) -> 42118
A39: 526886 | B39: ARX Everest Advisory | C39: 35.789.436/0001-96 | D39: =INDEX(Planilha2!$E:$E,MATCH(CAPA!A39,Planilha2!$D:$D,0)) -> Renda Fixa Duração Baixa Grau de Investimento | E39: =INDEX(Planilha2!$F:$F,MATCH(CAPA!A39,Planilha2!$D:$D,0)) -> ARX Investimentos Ltda. | F39: =INDEX(Planilha2!$G:$G,MATCH(CAPA!A39,Planilha2!$D:$D,0)) -> BNY Mellon Serviços Financeiros Dtvm S/A | G39: =INDEX(Planilha2!$H:$H,MATCH(CAPA!A39,Planilha2!$D:$D,0)) -> 0 | H39: =(_xlfn.XLOOKUP(A39,Cotas!$C$1:$C$27,Cotas!$E$1:$E$27)/_xlfn.XLOOKUP(A39,Cotas!$C$1:$C$27,Cotas!$F$1:$F$27))-1 -> 0.012434786 | I39: =(INDEX(Planilha2!$J:$J,MATCH(A39,Planilha2!$D:$D,0)))/1-1 -> 0.94181722 | J39: =INDEX(Planilha2!$L:$L,MATCH(CAPA!A39,Planilha2!$D:$D,0)) -> 1.0987365 | K39: =INDEX(Planilha2!$M:$M,MATCH(CAPA!A39,Planilha2!$D:$D,0)) -> 424848.58 | L39: =INDEX(Planilha2!$K:$K,MATCH(CAPA!A39,Planilha2!$D:$D,0)) -> 43866
A40: 414972 | B40: Polo Total | C40: 23.601.467/0001-92 | D40: =INDEX(Planilha2!$E:$E,MATCH(CAPA!A40,Planilha2!$D:$D,0)) -> Multimercados Livre | E40: =INDEX(Planilha2!$F:$F,MATCH(CAPA!A40,Planilha2!$D:$D,0)) -> Polo Capital Gestão de Recurso | F40: =INDEX(Planilha2!$G:$G,MATCH(CAPA!A40,Planilha2!$D:$D,0)) -> BNY Mellon Serviços Financeiros Dtvm S/A | G40: =INDEX(Planilha2!$H:$H,MATCH(CAPA!A40,Planilha2!$D:$D,0)) -> 0 | H40: =(_xlfn.XLOOKUP(A40,Cotas!$C$1:$C$27,Cotas!$E$1:$E$27)/_xlfn.XLOOKUP(A40,Cotas!$C$1:$C$27,Cotas!$F$1:$F$27))-1 -> 0.010883758 | I40: =(INDEX(Planilha2!$J:$J,MATCH(A40,Planilha2!$D:$D,0)))/1-1 -> 2.2810512 | J40: =INDEX(Planilha2!$L:$L,MATCH(CAPA!A40,Planilha2!$D:$D,0)) -> 3.2466781 | K40: =INDEX(Planilha2!$M:$M,MATCH(CAPA!A40,Planilha2!$D:$D,0)) -> 73457.618 | L40: =INDEX(Planilha2!$K:$K,MATCH(CAPA!A40,Planilha2!$D:$D,0)) -> 42432
A41: 687138 | B41: Absolute Olimpia | C41: 48.986.106/0001-32 | D41: =INDEX(Planilha2!$E:$E,MATCH(CAPA!A41,Planilha2!$D:$D,0)) -> Multimercados Livre | E41: =INDEX(Planilha2!$F:$F,MATCH(CAPA!A41,Planilha2!$D:$D,0)) -> Absolute Crédito | F41: =INDEX(Planilha2!$G:$G,MATCH(CAPA!A41,Planilha2!$D:$D,0)) -> BTG Pactual Servicos Financeiros S/A Dtv | G41: =INDEX(Planilha2!$H:$H,MATCH(CAPA!A41,Planilha2!$D:$D,0)) -> 0 | H41: =(_xlfn.XLOOKUP(A41,Cotas!$C$1:$C$27,Cotas!$E$1:$E$27)/_xlfn.XLOOKUP(A41,Cotas!$C$1:$C$27,Cotas!$F$1:$F$27))-1 -> 0.0066569517 | I41: =(INDEX(Planilha2!$J:$J,MATCH(A41,Planilha2!$D:$D,0)))/1-1 -> 0.583209 | J41: =INDEX(Planilha2!$L:$L,MATCH(CAPA!A41,Planilha2!$D:$D,0)) -> 0.61119382 | K41: =INDEX(Planilha2!$M:$M,MATCH(CAPA!A41,Planilha2!$D:$D,0)) -> 272263.43 | L41: =INDEX(Planilha2!$K:$K,MATCH(CAPA!A41,Planilha2!$D:$D,0)) -> 44925

Sheet Cotas
B1: {=_xll.ECONOMATICA(_xll.EcoRange(1,-1,26,-1),"Name",,,,,,,"false","true")} -> Nome | C1: {=_xll.ECONOMATICA(_xll.EcoRange(1,-2,26,-2),"Codigo de Fundo CVM 555/2014",,,,,,,"false","true")} -> Codigo de Fundo CVM 555/2014 | D1: {=_xll.ECONOMATICA(_xll.EcoRange(1,-3,26,-3),"Close",,"D-0",,,"ORIGINAL CURRENCY",,"false","true","Cota em reais",{"tc.pers=3"})} -> Cota em reais | E1: {=_xll.ECONOMATICA(_xll.EcoRange(1,-4,26,-4),"Close",,"2026-04-30",,,"ORIGINAL CURRENCY",,"false","true")} -> Fechamento 30Abr26 ajust p/ prov Em moeda orig | F1: {=_xll.ECONOMATICA(_xll.EcoRange(1,-5,26,-5),"Close",,"2026-03-31",,,"ORIGINAL CURRENCY",,"false","true")} -> Fechamento 31Mar26 ajust p/ prov Em moeda orig | G1: {=_xll.ECONOMATICA(_xll.EcoRange(1,-6,26,-6),"Close",,"2008-09-11",,,"ORIGINAL CURRENCY",,"false","true")} -> Fechamento 11Set08 ajust p/ prov Em moeda orig | H1: {=_xll.ECONOMATICA(_xll.EcoRange(1,-7,26,-7),"Close",,"2021-08-05",,,"ORIGINAL CURRENCY",,"false","true")} -> Fechamento 05Ago21 ajust p/ prov Em moeda orig | I1: {=_xll.ECONOMATICA(_xll.EcoRange(1,-8,26,-8),"Close",,"2011-08-22",,,"ORIGINAL CURRENCY",,"false","true")} -> Fechamento 22Ago11 ajust p/ prov Em moeda orig | J1: {=_xll.ECONOMATICA(_xll.EcoRange(1,-9,26,-9),"Close",,"2020-03-17",,,"ORIGINAL CURRENCY",,"false","true")} -> Fechamento 17Mar20 ajust p/ prov Em moeda orig | K1: {=_xll.ECONOMATICA(_xll.EcoRange(1,-10,26,-10),"Close",,"2019-03-14",,,"ORIGINAL CURRENCY",,"false","true")} -> Fechamento 14Mar19 ajust p/ prov Em moeda orig | L1: {=_xll.ECONOMATICA(_xll.EcoRange(1,-11,26,-11),"Close",,"2010-07-30",,,"ORIGINAL CURRENCY",,"false","true")} -> Fechamento 30Jul10 ajust p/ prov Em moeda orig | M1: {=_xll.ECONOMATICA(_xll.EcoRange(1,-12,26,-12),"Close",,"2017-11-08",,,"ORIGINAL CURRENCY",,"false","true")} -> Fechamento 08Nov17 ajust p/ prov Em moeda orig | N1: {=_xll.ECONOMATICA(_xll.EcoRange(1,-13,26,-13),"Close",,"2014-02-28",,,"ORIGINAL CURRENCY",,"false","true")} -> Fechamento 28Fev14 ajust p/ prov Em moeda orig | O1: {=_xll.ECONOMATICA(_xll.EcoRange(1,-14,26,-14),"Close",,"2022-01-13",,,"ORIGINAL CURRENCY",,"false","true")} -> Fechamento 13Jan22 ajust p/ prov Em moeda orig | P1: {=_xll.ECONOMATICA(_xll.EcoRange(1,-15,26,-15),"Close",,"2015-01-30",,,"ORIGINAL CURRENCY",,"false","true")} -> Fechamento 30Jan15 ajust p/ prov Em moeda orig | Q1: {=_xll.ECONOMATICA(_xll.EcoRange(1,-16,26,-16),"Close",,"2022-10-28",,,"ORIGINAL CURRENCY",,"false","true")} -> Fechamento 28Out22 ajust p/ prov Em moeda orig | R1: {=_xll.ECONOMATICA(_xll.EcoRange(1,-17,26,-17),"Close",,"2018-03-28",,,"ORIGINAL CURRENCY",,"false","true")} -> Fechamento 28Mar18 ajust p/ prov Em moeda orig | S1: {=_xll.ECONOMATICA(_xll.EcoRange(1,-18,26,-18),"Close",,"2018-07-02",,,"ORIGINAL CURRENCY",,"false","true")} -> Fechamento 02Jul18 ajust p/ prov Em moeda orig | T1: {=_xll.ECONOMATICA(_xll.EcoRange(1,-19,26,-19),"Close",,"2021-10-29",,,"ORIGINAL CURRENCY",,"false","true")} -> Fechamento 29Out21 ajust p/ prov Em moeda orig | U1: {=_xll.ECONOMATICA(_xll.EcoRange(1,-20,26,-20),"Close",,"2021-07-16",,,"ORIGINAL CURRENCY",,"false","true")} -> Fechamento 16Jul21 ajust p/ prov Em moeda orig | V1: {=_xll.ECONOMATICA(_xll.EcoRange(1,-21,26,-21),"Close",,"2019-04-30",,,"ORIGINAL CURRENCY",,"false","true")} -> Fechamento 30Abr19 ajust p/ prov Em moeda orig | W1: {=_xll.ECONOMATICA(_xll.EcoRange(1,-22,26,-22),"Close",,"2018-10-22",,,"ORIGINAL CURRENCY",,"false","true")} -> Fechamento 22Out18 ajust p/ prov Em moeda orig | X1: {=_xll.ECONOMATICA(_xll.EcoRange(1,-23,26,-23),"Close",,"2019-05-06",,,"ORIGINAL CURRENCY",,"false","true")} -> Fechamento 06Mai19 ajust p/ prov Em moeda orig | Y1: {=_xll.ECONOMATICA(_xll.EcoRange(1,-24,26,-24),"Close",,"2019-11-29",,,"ORIGINAL CURRENCY",,"false","true")} -> Fechamento 29Nov19 ajust p/ prov Em moeda orig | Z1: {=_xll.ECONOMATICA(_xll.EcoRange(1,-25,26,-25),"Close",,"2019-04-24",,,"ORIGINAL CURRENCY",,"false","true")} -> Fechamento 24Abr19 ajust p/ prov Em moeda orig | AA1: {=_xll.ECONOMATICA(_xll.EcoRange(1,-26,26,-26),"Close",,"2022-10-28",,,"ORIGINAL CURRENCY",,"false","true")} -> Fechamento 28Out22 ajust p/ prov Em moeda orig | AB1: {=_xll.ECONOMATICA(_xll.EcoRange(1,-27,26,-27),"Close",,"2021-11-23",,,"ORIGINAL CURRENCY",,"false","true")} -> Fechamento 23Nov21 ajust p/ prov Em moeda orig | AC1: {=_xll.ECONOMATICA(_xll.EcoRange(1,-28,26,-28),"Close",,"2015-04-24",,,"ORIGINAL CURRENCY",,"false","true")} -> Fechamento 24Abr15 ajust p/ prov Em moeda orig | AD1: {=_xll.ECONOMATICA(_xll.EcoRange(1,-29,26,-29),"Close",,"2020-02-05",,,"ORIGINAL CURRENCY",,"false","true")} -> Fechamento 05Fev20 ajust p/ prov Em moeda orig | AE1: {=_xll.ECONOMATICA(_xll.EcoRange(1,-30,26,-30),"Close",,"2016-03-03",,,"ORIGINAL CURRENCY",,"false","true")} -> Fechamento 03Mar16 ajust p/ prov Em moeda orig | AF1: {=_xll.ECONOMATICA(_xll.EcoRange(1,-31,26,-31),"Close",,"2022-12-30",,,"ORIGINAL CURRENCY",,"false","true")} -> Fechamento 30Dez22 ajust p/ prov Em moeda orig
A2: 634468<BraNa> | B2: ARX Denali Advisory Fc FIF RF Créd Priv - Resp Lim | C2: 634468 | D2: 1.7662261 | E2: 1.7596242 | F2: 1.7398308 | H2: 1 | O2: 1.03784 | Q2: 1.1479735 | T2: 1.0187029 | AA2: 1.1479735 | AB2: 1.0242116 | AF2: 1.1747173
A3: 526886<BraNa> | B3: ARX Everest Advisory Fc FIF RF Cred Priv - Resp Limitada | C3: 526886 | D3: 1.9418172 | E3: 1.9328767 | F3: 1.909137 | H3: 1.0852229 | J3: 1.0041849 | O3: 1.1345051 | Q3: 1.2711617 | T3: 1.1121076 | U3: 1.0810026 | AA3: 1.2711617 | AB3: 1.1187369 | AD3: 1 | AF3: 1.3038299
A4: 601462<BraNa> | B4: ARX Vinson Adv Fc FIF RF Cred Priv - Resp Limitada | C4: 601462 | D4: 1.7933704 | E4: 1.7857214 | F4: 1.7646938 | H4: 1.0041692 | O4: 1.0455768 | Q4: 1.1633393 | T4: 1.0265266 | U4: 1 | AA4: 1.1633393 | AB4: 1.0322547 | AF4: 1.1915017
A5: 284491<BraNa> | B5: Capitânia Top Cred Priv Fc FIF RF - Resp Limitada | C5: 284491 | D5: 5.3371224 | E5: 5.3329019 | F5: 5.2595358 | G5: 1.0376291 | H5: 3.2774151 | I5: 1.3931199 | J5: 3.1445395 | K5: 2.9588625 | L5: 1.2444763 | M5: 2.7140413 | N5: 1.7445266 | O5: 3.389947 | P5: 1.927868 | Q5: 3.7506474 | R5: 2.7831627 | S5: 2.8307033 | T5: 3.3261074 | U5: 3.2723491 | V5: 2.9901916 | W5: 2.8903311 | X5: 2.9959838 | Y5: 3.1011553 | Z5: 2.98809 | AA5: 3.7506474 | AB5: 3.3408209 | AC5: 1.9818129 | AD5: 3.1440475 | AE5: 2.222434 | AF5: 3.8267769
A6: 677930<BraNa> | B6: Classe Única de Cotas do Absolute Atenas Advisory FI Financeiro em Cota | C6: 677930 | D6: 1.5686397 | E6: 1.5629491 | F6: 1.5475839 | Q6: 1 | AA6: 1 | AF6: 1.0253053
A7: 678007<BraNa> | B7: Classe Única de Cotas do Absolute Creta Advisory F | C7: 678007 | D7: 1.5859878 | E7: 1.5783773 | F7: 1.5653216 | Q7: 1 | AA7: 1 | AF7: 1.0264306
A8: 687138<BraNa> | B8: Classe Única de Cotas do Absolute Olimpia Fundo de | C8: 687138 | D8: 1.583209 | E8: 1.5746727 | F8: 1.5642595 | AF8: 1
A9: 624977<BraNa> | B9: Classe Unica de Cotas do Af Horizonte Fundo de Inv | C9: 624977 | D9: 1.7252344 | E9: 1.7186055 | F9: 1.7002944 | O9: 1.0147108 | Q9: 1.1318189 | AA9: 1.1318189 | AB9: 1 | AF9: 1.1627989
A10: 462276<BraNa> | B10: Classe Única de Cotas do Af Invest Geraes 30 FI Financeiro RF - | C10: 462276 | D10: 2.0633091 | E10: 2.0579606 | F10: 2.0387755 | H10: 1.1603029 | J10: 1.1432 | K10: 1.0810049 | O10: 1.2125659 | Q10: 1.3521019 | R10: 1 | S10: 1.0211474 | T10: 1.1890657 | U10: 1.1557507 | V10: 1.0918319 | W10: 1.046623 | X10: 1.0928351 | Y10: 1.1298742 | Z10: 1.0906562 | AA10: 1.3521019 | AB10: 1.1945714 | AD10: 1.1399037 | AF10: 1.3857632
A11: 216658<BraNa> | B11: Classe Única de Cotas do Af Invest Geraes FI Financeiro RF - Cr | C11: 216658 | D11: 5.4968332 | E11: 5.4794122 | F11: 5.4244737 | G11: 1 | H11: 3.1170978 | I11: 1.3531213 | J11: 3.1129841 | K11: 2.9505964 | L11: 1.2034764 | M11: 2.6776805 | N11: 1.6936277 | O11: 3.2399192 | P11: 1.8739934 | Q11: 3.587904 | R11: 2.7565564 | S11: 2.8081113 | T11: 3.176071 | U11: 3.1085499 | V11: 2.9767967 | W11: 2.8698934 | X11: 2.9791148 | Y11: 3.0766021 | Z11: 2.9736519 | AA11: 3.587904 | AB11: 3.1936204 | AC11: 1.9262156 | AD11: 3.1029164 | AE11: 2.1605678 | AF11: 3.6723392
A12: 531553<BraNa> | B12: Classe Única de Cotas do Riza Lotus Fundo de Inves | C12: 531553 | D12: 1.9132096 | E12: 1.9068678 | F12: 1.8869123 | H12: 1.0690978 | J12: 1 | O12: 1.1075429 | Q12: 1.2279518 | T12: 1.0869528 | U12: 1.0658752 | AA12: 1.2279518 | AB12: 1.0923853 | AF12: 1.2570698
A13: 620955<BraNa> | B13: Classe Única de Cotas do Riza Lotus Plus Advisory | C13: 620955 | D13: 1.7399199 | E13: 1.7336763 | F13: 1.7162036 | O13: 1.0192348 | Q13: 1.1402935 | T13: 1 | AA13: 1.1402935 | AB13: 1.0047928 | AF13: 1.167346
A14: 489956<BraNa> | B14: Classe Única do Western Asset Total Credit Advisory FIC de Fund | C14: 489956 | D14: 1926.6212 | E14: 1919.9762 | F14: 1899.6821 | H14: 1098.5341 | J14: 1050.4205 | K14: 1000 | O14: 1138.1354 | Q14: 1254.2617 | T14: 1118.1654 | U14: 1094.6379 | V14: 1008.3999 | X14: 1009.1107 | Y14: 1040.2909 | Z14: 1007.3807 | AA14: 1254.2617 | AB14: 1123.57 | AD14: 1048.5353 | AF14: 1283.2574
A15: 470473<BraNa> | B15: Daycoval Classic 30 Classe de Investimento RF Cred Priv Resp Limitada | C15: 470473 | D15: 2.1051864 | E15: 2.096794 | F15: 2.0740522 | H15: 1.167166 | J15: 1.1114943 | K15: 1.0511561 | O15: 1.2154212 | Q15: 1.35428 | S15: 1 | T15: 1.1928621 | U15: 1.1631933 | V15: 1.0606729 | W15: 1.0219334 | X15: 1.0615014 | Y15: 1.0981563 | Z15: 1.059439 | AA15: 1.35428 | AB15: 1.199012 | AD15: 1.1075018 | AF15: 1.3874848
A16: 259624<BraNa> | B16: Daycoval Classic Classe de Investimento em Cotas de FI RF Cred Priv Resp Limitada Cred Pri | C16: 259624 | D16: 5.3789138 | E16: 5.3594202 | F16: 5.3058312 | H16: 3.0086899 | I16: 1.2705581 | J16: 2.9012443 | K16: 2.7515541 | L16: 1.1238687 | M16: 2.5120232 | N16: 1.5960995 | O16: 3.1337198 | P16: 1.7675141 | Q16: 3.4707498 | R16: 2.5805977 | S16: 2.6260887 | T16: 3.0763409 | U16: 3.0002828 | V16: 2.7754854 | W16: 2.6808647 | X16: 2.7776527 | Y16: 2.8677603 | Z16: 2.772409 | AA16: 3.4707498 | AB16: 3.0929515 | AC16: 1.815986 | AD16: 2.8920333 | AE16: 2.0424795 | AF16: 3.5525322
A17: 387444<BraNa> | B17: Inter Conservador FI Financeiro RF Cred Priv Responsabili | C17: 387444 | D17: 2.9001288 | E17: 2.890326 | F17: 2.8584807 | H17: 1.6404836 | J17: 1.6397131 | K17: 1.5599019 | M17: 1.41946 | O17: 1.7175551 | P17: 1 | Q17: 1.9025287 | R17: 1.4603639 | S17: 1.4858081 | T17: 1.6854669 | U17: 1.6363924 | V17: 1.5739439 | W17: 1.5168075 | X17: 1.5751644 | Y17: 1.6208548 | Z17: 1.5720385 | AA17: 1.9025287 | AB17: 1.6944535 | AC17: 1.0281902 | AD17: 1.6342917 | AE17: 1.1511147 | AF17: 1.9467134
A18: 456497<BraNa> | B18: Iridium Apollo Fc FIF RF Cred Priv LP - Resp Limitada | C18: 456497 | D18: 2.0870277 | E18: 2.0789638 | F18: 2.0543316 | H18: 1.1705748 | J18: 1.1557277 | K18: 1.0956521 | M18: 1 | O18: 1.2188151 | Q18: 1.3518119 | R18: 1.0263257 | S18: 1.0447617 | T18: 1.1960899 | U18: 1.1671358 | V18: 1.1048857 | W18: 1.0679714 | X18: 1.1057342 | Y18: 1.1418903 | Z18: 1.1037424 | AA18: 1.3518119 | AB18: 1.2025499 | AD18: 1.1521682 | AF18: 1.3827569
A19: 494607<BraNa> | B19: Iridium Titan Advisory Fc FIF RF Cred Priv ? Resp Limitada | C19: 494607 | D19: 2.0185206 | E19: 2.0097619 | F19: 1.9848059 | H19: 1.1105647 | J19: 1.0599083 | O19: 1.1580956 | Q19: 1.294147 | T19: 1.1337464 | U19: 1.1085087 | X19: 1 | Y19: 1.04438 | AA19: 1.294147 | AB19: 1.140574 | AD19: 1.0556855 | AF19: 1.3247278
A20: 393185<BraNa> | B20: Jgp Select Fc FIF Mult Cred Priv - Resp Limitada | C20: 393185 | D20: 321.29301 | E20: 320.05517 | F20: 316.57313 | H20: 176.1598 | J20: 161.29744 | K20: 160.75708 | M20: 145.92255 | O20: 181.24742 | Q20: 200.9787 | R20: 150.09619 | S20: 151.29689 | T20: 178.3181 | U20: 175.57956 | V20: 162.48553 | W20: 155.36069 | X20: 162.70294 | Y20: 169.18064 | Z20: 162.32214 | AA20: 200.9787 | AB20: 178.96141 | AC20: 100 | AD20: 171.83371 | AE20: 111.57078 | AF20: 206.15913
A21: 635091<BraNa> | B21: Nu Reserva Imediata FIF Cic RF Ref DI Resp Limitad | C21: 635091 | D21: 1.6933984 | E21: 1.6876813 | F21: 1.6710274 | O21: 1 | Q21: 1.1052 | AA21: 1.1052 | AF21: 1.1303088
A22: 478008<BraNa> | B22: Polo Crédito Corporativo Advisory Fc FIF RF Cred Priv LP - Resp Limitada | C22: 478008 | D22: 2.1123136 | E22: 2.1027397 | F22: 2.0855805 | H22: 1.1466894 | J22: 1.0902718 | K22: 1.0287687 | O22: 1.1908956 | Q22: 1.3287863 | T22: 1.1668217 | U22: 1.1430366 | V22: 1.0381126 | W22: 1 | X22: 1.0392395 | Y22: 1.0757625 | Z22: 1.0369996 | AA22: 1.3287863 | AB22: 1.1729875 | AD22: 1.085636 | AF22: 1.3635508
A23: 414972<BraNa> | B23: Polo Total Credit Fc FIF Mult Cred Priv - Resp Limitada | C23: 414972 | D23: 3.2810512 | E23: 3.2609409 | F23: 3.2258317 | H23: 1.7824117 | J23: 1.755066 | K23: 1.7681083 | M23: 1.5789675 | O23: 1.8446641 | Q23: 2.0312108 | R23: 1.6277879 | S23: 1.6215153 | T23: 1.8112538 | U23: 1.7745306 | V23: 1.7703122 | W23: 1.6819346 | X23: 1.768787 | Y23: 1.8005517 | Z23: 1.7742308 | AA23: 2.0312108 | AB23: 1.8110253 | AD23: 1.8468588 | AE23: 1 | AF23: 2.1155798
A24: 361445<BraNa> | B24: Porto Seguro FIF RF Ref DI Créd Priv Resp Limitada | C24: 361445 | D24: 3.3245078 | E24: 3.3118774 | F24: 3.27599 | H24: 1.8674479 | J24: 1.783959 | K24: 1.6998689 | M24: 1.5611625 | N24: 1 | O24: 1.9342799 | P24: 1.1068634 | Q24: 2.1324501 | R24: 1.600364 | S24: 1.626039 | T24: 1.9009911 | U24: 1.8611794 | V24: 1.7133436 | W24: 1.6576105 | X24: 1.7145569 | Y24: 1.7664313 | Z24: 1.7116829 | AA24: 2.1324501 | AB24: 1.9098298 | AC24: 1.1369556 | AD24: 1.7787758 | AE24: 1.2748607 | AF24: 2.1822407
A25: 523666<BraNa> | B25: Porto Seguro Ipê FIF da Cic RF Créd Priv LP Resp Limitada | C25: 523666 | D25: 194.54252 | E25: 193.73479 | F25: 191.46556 | H25: 106.89639 | J25: 101.31827 | O25: 111.13695 | Q25: 123.18813 | T25: 109.12749 | U25: 106.53933 | Y25: 100 | AA25: 123.18813 | AB25: 109.61703 | AD25: 100.99835 | AF25: 126.20597
A26: 493831<BraNa> | B26: Sparta Max Advisory Fc FIF RF Cred Priv LP - Resp Limitada | C26: 493831 | D26: 2.034299 | E26: 2.0268092 | F26: 2.0030389 | H26: 1.1237128 | J26: 1.0543433 | O26: 1.1687045 | Q26: 1.3012804 | T26: 1.1451667 | U26: 1.1186403 | V26: 1 | X26: 1.0008348 | Y26: 1.0377731 | AA26: 1.3012804 | AB26: 1.152018 | AD26: 1.0493124 | AF26: 1.3317299
A27: 494089<BraNa> | B27: Sparta Top Adv Fc FI RF Cred Priv LP - Resp Limitada | C27: 494089 | D27: 1.9438378 | E27: 1.937052 | F27: 1.9162951 | H27: 1.0902237 | J27: 1.0410712 | O27: 1.1325748 | Q27: 1.256001 | T27: 1.1112434 | U27: 1.0858749 | V27: 1.0010016 | X27: 1.0018592 | Y27: 1.0296385 | Z27: 1 | AA27: 1.256001 | AB27: 1.1173087 | AD27: 1.0389817 | AF27: 1.2844498

Sheet Planilha2
B1: {=_xll.ECONOMATICA(_xll.EcoRange(1,-1,26,-1),"Name",,,,,,,"false","true")} -> Nome | C1: {=_xll.ECONOMATICA(_xll.EcoRange(1,-2,26,-2),"Employer ID number",,,,,,,"false","true")} -> CNPJ | D1: {=_xll.ECONOMATICA(_xll.EcoRange(1,-3,26,-3),"Ticker",,,,,,,"false","true","Código Anbima")} -> Código Anbima | E1: {=_xll.ECONOMATICA(_xll.EcoRange(1,-4,26,-4),"Anbima classification",,,,,,,"false","true")} -> Classificação Anbima | F1: {=_xll.ECONOMATICA(_xll.EcoRange(1,-5,26,-5),"Fund manager",,,,,,,"false","true","Gestora ")} -> Gestora | G1: {=_xll.ECONOMATICA(_xll.EcoRange(1,-6,26,-6),"Administrator",,,,,,,"false","true")} -> Administradora | H1: {=_xll.ECONOMATICA(_xll.EcoRange(1,-7,26,-7),"Max management fee %/year",,,,,,,"false","true","Taxa de Administração Máxima em % a.a.")} -> Taxa de Administração Máxima em % a.a. | I1: {=_xll.ECONOMATICA(_xll.EcoRange(1,-8,26,-8),"Close",,"D-0",,,"ORIGINAL CURRENCY",,"false","true")} -> Fechamento 12Mai26 ajust p/ prov Em moeda orig | J1: {=_xll.ECONOMATICA(_xll.EcoRange(1,-9,26,-9),"Close",,"LATEST",,,"ORIGINAL CURRENCY",,"false","true","Cota em reais",{"tc.pers=3"})} -> Cota em reais | K1: {=_xll.ECONOMATICA(_xll.EcoRange(1,-10,26,-10),"Series Start Date",,,,,,,"false","true")} -> Data do Início da Série | L1: {=_xll.ECONOMATICA(_xll.EcoRange(1,-11,26,-11),"Volatility","FROM START","D-0",,,"ORIGINAL CURRENCY",,"false","true")} -> Volatilidade base anual 12Mai26 desde início Em moeda orig | M1: {=_xll.ECONOMATICA(_xll.EcoRange(1,-12,26,-12),"Net Assets",,"LATEST",,,"ORIGINAL CURRENCY","THOUSANDS","false","true")} -> Patrimônio Mais recente Em moeda orig em milhares
A2: 634468<BraNa> | B2: ARX Denali Advisory Fc FIF RF Créd Priv - Resp Lim | C2: 41888219000156 | D2: 634468 | E2: Renda Fixa Duração Baixa Grau de Investimento | F2: ARX Investimentos Ltda. | G2: BNY Mellon Serviços Financeiros Dtvm S/A | J2: 1.7662261 | K2: 44413 | L2: 0.370749 | M2: 1598464.3
A3: 526886<BraNa> | B3: ARX Everest Advisory Fc FIF RF Cred Priv - Resp Limitada | C3: 35789436000196 | D3: 526886 | E3: Renda Fixa Duração Baixa Grau de Investimento | F3: ARX Investimentos Ltda. | G3: BNY Mellon Serviços Financeiros Dtvm S/A | J3: 1.9418172 | K3: 43866 | L3: 1.0987365 | M3: 424848.58
A4: 601462<BraNa> | B4: ARX Vinson Adv Fc FIF RF Cred Priv - Resp Limitada | C4: 41888492000180 | D4: 601462 | E4: Renda Fixa Duração Baixa Grau de Investimento | F4: ARX Investimentos Ltda. | G4: BNY Mellon Serviços Financeiros Dtvm S/A | J4: 1.7933704 | K4: 44393 | L4: 0.52976793 | M4: 1251713.9
A5: 284491<BraNa> | B5: Capitânia Top Cred Priv Fc FIF RF - Resp Limitada | C5: 13615411000133 | D5: 284491 | E5: Renda Fixa Duração Média Crédito Livre | F5: Capitania Capital | G5: BNY Mellon Serviços Financeiros Dtvm S/A | J5: 5.3371224 | K5: 39589 | L5: 0.88878195 | M5: 203260.47
A6: 677930<BraNa> | B6: Classe Única de Cotas do Absolute Atenas Advisory FI Financeiro em Cota | C6: 48096589000108 | D6: 677930 | E6: Renda Fixa Duração Baixa Grau de Investimento | F6: Absolute Crédito | G6: BTG Pactual Servicos Financeiros S/A Dtv | J6: 1.5686397 | K6: 44862 | L6: 0.26345109 | M6: 734275.08
A7: 678007<BraNa> | B7: Classe Única de Cotas do Absolute Creta Advisory F | C7: 48122126000165 | D7: 678007 | E7: Renda Fixa Duração Baixa Grau de Investimento | F7: Absolute Crédito | G7: BTG Pactual Servicos Financeiros S/A Dtv | J7: 1.5859878 | K7: 44862 | L7: 0.4832305 | M7: 1721026.5
A8: 687138<BraNa> | B8: Classe Única de Cotas do Absolute Olimpia Fundo de | C8: 48986106000132 | D8: 687138 | E8: Multimercados Livre | F8: Absolute Crédito | G8: BTG Pactual Servicos Financeiros S/A Dtv | J8: 1.583209 | K8: 44925 | L8: 0.61119382 | M8: 272263.43
A9: 624977<BraNa> | B9: Classe Unica de Cotas do Af Horizonte Fundo de Inv | C9: 44025131000107 | D9: 624977 | E9: Multimercados Livre | F9: Af Invest Administração de Recursos Ltda | G9: BTG Pactual Servicos Financeiros S/A Dtv | J9: 1.7252344 | K9: 44523 | L9: 0.91291145 | M9: 230557.05
A10: 462276<BraNa> | B10: Classe Única de Cotas do Af Invest Geraes 30 FI Financeiro RF - | C10: 29044189000104 | D10: 462276 | E10: Renda Fixa Duração Livre Grau de Investimento | F10: Af Invest Administração de Recursos Ltda | G10: BTG Pactual Servicos Financeiros S/A Dtv | J10: 2.0633091 | K10: 43187 | L10: 1.101544 | M10: 311423.16
A11: 216658<BraNa> | B11: Classe Única de Cotas do Af Invest Geraes FI Financeiro RF - Cr | C11: 9720734000110 | D11: 216658 | E11: Renda Fixa Duração Livre Grau de Investimento | F11: Af Invest Administração de Recursos Ltda | G11: BTG Pactual Servicos Financeiros S/A Dtv | J11: 5.4968332 | K11: 39702 | L11: 0.63200306 | M11: 539746.11
A12: 531553<BraNa> | B12: Classe Única de Cotas do Riza Lotus Fundo de Inves | C12: 36498670000127 | D12: 531553 | E12: Renda Fixa Duração Livre Grau de Investimento | F12: Riza Líquidos | G12: BTG Pactual Servicos Financeiros S/A Dtv | H12: 0.4 | J12: 1.9132096 | K12: 43907 | L12: 0.33481661 | M12: 3801596.9
A13: 620955<BraNa> | B13: Classe Única de Cotas do Riza Lotus Plus Advisory | C13: 43917493000131 | D13: 620955 | E13: Renda Fixa Duração Livre Grau de Investimento | F13: Riza Líquidos | G13: BTG Pactual Servicos Financeiros S/A Dtv | J13: 1.7399199 | K13: 44498 | L13: 0.89491432 | M13: 498517.97
A14: 489956<BraNa> | B14: Classe Única do Western Asset Total Credit Advisory FIC de Fund | C14: 28320756000137 | D14: 489956 | E14: Renda Fixa Duração Baixa Grau de Investimento | F14: Franklin Templeton Brasil Ltda | G14: Banco BNP Paribas Brasil S/A | J14: 1926.6212 | K14: 43538 | L14: 0.78192199 | M14: 3569168.5
A15: 470473<BraNa> | B15: Daycoval Classic 30 Classe de Investimento RF Cred Priv Resp Limitada | C15: 29250121000173 | D15: 470473 | E15: Renda Fixa Duração Baixa Grau de Investimento | F15: Daycoval Asset Manag | G15: Banco Daycoval S.A. | J15: 2.1051864 | K15: 43283 | L15: 0.60675787 | M15: 865976.73
A16: 259624<BraNa> | B16: Daycoval Classic Classe de Investimento em Cotas de FI RF Cred Priv Resp Limitada Cred Pri | C16: 10783480000168 | D16: 259624 | E16: Renda Fixa Duração Baixa Grau de Investimento | F16: Daycoval Asset Manag | G16: Banco Daycoval S.A. | J16: 5.3789138 | K16: 40389 | L16: 0.38517713 | M16: 2164491.5
A17: 387444<BraNa> | B17: Inter Conservador FI Financeiro RF Cred Priv Responsabili | C17: 20879578000177 | D17: 387444 | E17: Renda Fixa Duração Baixa Grau de Investimento | F17: Inter Asset | G17: Inter Distribuidora de Títulos e Valores | J17: 2.9001288 | K17: 42034 | L17: 0.82942731 | M17: 1344300.3
A18: 456497<BraNa> | B18: Iridium Apollo Fc FIF RF Cred Priv LP - Resp Limitada | C18: 26978438000132 | D18: 456497 | E18: Renda Fixa Duração Livre Grau de Investimento | F18: Iridium Gestão de Recursos Ltda. | G18: BNY Mellon Serviços Financeiros Dtvm S/A | J18: 2.0870277 | K18: 43047 | L18: 0.88568006 | M18: 1387027
A19: 494607<BraNa> | B19: Iridium Titan Advisory Fc FIF RF Cred Priv ? Resp Limitada | C19: 32756812000158 | D19: 494607 | E19: Renda Fixa Duração Livre Crédito Livre | F19: Iridium Gestão de Recursos Ltda. | G19: BNY Mellon Serviços Financeiros Dtvm S/A | J19: 2.0185206 | K19: 43591 | L19: 0.67011672 | M19: 187499.27
A20: 393185<BraNa> | B20: Jgp Select Fc FIF Mult Cred Priv - Resp Limitada | C20: 21946695000179 | D20: 393185 | E20: Multimercados Estratégia Específica | F20: Jgp Gestão de Crédito Ltda. | G20: BNY Mellon Serviços Financeiros Dtvm S/A | J20: 321.29301 | K20: 42118 | L20: 1.5295323 | M20: 347114.09
A21: 635091<BraNa> | B21: Nu Reserva Imediata FIF Cic RF Ref DI Resp Limitad | C21: 42699466000177 | D21: 635091 | E21: Renda Fixa Duração Baixa Grau de Investimento | F21: Nu Asset Management Ltda. | G21: Intrag Dist. de Títu | J21: 1.6933984 | K21: 44574 | L21: 0.44668576 | M21: 2834785.7
A22: 478008<BraNa> | B22: Polo Crédito Corporativo Advisory Fc FIF RF Cred Priv LP - Resp Limitada | C22: 31455879000190 | D22: 478008 | E22: Renda Fixa Duração Livre Crédito Livre | F22: Polo Capital Gestão de Recurso | G22: BNY Mellon Serviços Financeiros Dtvm S/A | J22: 2.1123136 | K22: 43395 | L22: 0.6130043 | M22: 1157810.9
A23: 414972<BraNa> | B23: Polo Total Credit Fc FIF Mult Cred Priv - Resp Limitada | C23: 23601467000192 | D23: 414972 | E23: Multimercados Livre | F23: Polo Capital Gestão de Recurso | G23: BNY Mellon Serviços Financeiros Dtvm S/A | J23: 3.2810512 | K23: 42432 | L23: 3.2466781 | M23: 73457.618
A24: 361445<BraNa> | B24: Porto Seguro FIF RF Ref DI Créd Priv Resp Limitada | C24: 18719154000101 | D24: 361445 | E24: Renda Fixa Duração Baixa Grau de Investimento | F24: Porto Seguro Investimentos Ltda. | G24: Intrag Dist. de Títu | J24: 3.3245078 | K24: 41698 | L24: 0.54447902 | M24: 6892815.2
... A27: 494089<BraNa> | B27: Sparta Top Adv Fc FI RF Cred Priv LP - Resp Limitada | C27: 32846811000102 | D27: 494089 | E27: Renda Fixa Duração Média Grau de Investimento | F27: Sparta Administradora de Recursos Ltda | G27: BNY Mellon Serviços Financeiros Dtvm S/A | J27: 1.9438378 | K27: 43579 | L27: 0.83844845 | M27: 574548.93

Sheet Correlação
B1: {=_xll.ECONOMATICA(_xll.EcoRange(1,-1,26,-1),"Name",,,,,,,"false","true")} -> Nome | C1: {=_xll.ECONOMATICA(_xll.EcoRange(1,-2,26,-2),"Correlation","12M","LATEST",,,"ORIGINAL CURRENCY",,"false","true",,{"jtc.per=0";"std.tec.stt.bmk=0:160134,1:160134,2:160134,3:160134,4:160134,5:160134,6:160134,7:160134,";"std.tec.stt.bmk=8:160134,9:160134,10:160134,11:160134,12:160134,13:160134,14:160134,15:160134,16:160134,17:160134,18:160134,19:160134,20:160134,21:160134,22:160134,23:160134,24:160134,25:160134,26:160134,27:160134,28:160134,29:160134,30:160134,31:160134,3";"std.tec.stt.bmk=2:160134,33:160134,34:160134,35:160134,36:160134,37:160134,38:160134,39:160134,40:160134,41:160134,42:160134,43:160134,44:160134,45:160134,46:160134,47:160134,48:160134,49:160134,50:160134,51:160134,52:160134,53:160134,54:160134,55:160134,";"std.tec.stt.bmk=56:160134,57:160134,58:160134,59:160134,60:160134,61:160134,62:160134,63:160134,64:160134,65:160134,66:160134,67:160134,68:160134,69:160134,70:160134,71:160134,72:160134,73:160134,74:160134,75:160134,76:160134,77:160134,78:160134,79:160134"})} -> Correlacao Mais recente 12 meses Em moeda orig ARX Denali Advisory Fc FIF RF Créd Priv - Resp Lim | D1: {=_xll.ECONOMATICA(_xll.EcoRange(1,-3,26,-3),"Correlation","12M","LATEST",,,"ORIGINAL CURRENCY",,"false","true",,{"jtc.per=0";"std.tec.stt.bmk=0:137324,1:137324,2:137324,3:137324,4:137324,5:137324,6:137324,7:137324,";"std.tec.stt.bmk=8:137324,9:137324,10:137324,11:137324,12:137324,13:137324,14:137324,15:137324,16:137324,17:137324,18:137324,19:137324,20:137324,21:137324,22:137324,23:137324,24:137324,25:137324,26:137324,27:137324,28:137324,29:137324,30:137324,31:137324,3";"std.tec.stt.bmk=2:137324,33:137324,34:137324,35:137324,36:137324,37:137324,38:137324,39:137324,40:137324,41:137324,42:137324,43:137324,44:137324,45:137324,46:137324,47:137324,48:137324,49:137324,50:137324,51:137324,52:137324,53:137324,54:137324,55:137324,";"std.tec.stt.bmk=56:137324,57:137324,58:137324,59:137324,60:137324,61:137324,62:137324,63:137324,64:137324,65:137324,66:137324,67:137324,68:137324,69:137324,70:137324,71:137324,72:137324,73:137324,74:137324,75:137324,76:137324,77:137324,78:137324,79:137324"})} -> Correlacao Mais recente 12 meses Em moeda orig ARX Everest Advisory Fc FIF RF Cred Priv - Resp Limitada | E1: {=_xll.ECONOMATICA(_xll.EcoRange(1,-4,26,-4),"Correlation","12M","LATEST",,,"ORIGINAL CURRENCY",,"false","true",,{"jtc.per=0";"std.tec.stt.bmk=0:159179,1:159179,2:159179,3:159179,4:159179,5:159179,6:159179,7:159179,";"std.tec.stt.bmk=8:159179,9:159179,10:159179,11:159179,12:159179,13:159179,14:159179,15:159179,16:159179,17:159179,18:159179,19:159179,20:159179,21:159179,22:159179,23:159179,24:159179,25:159179,26:159179,27:159179,28:159179,29:159179,30:159179,31:159179,3";"std.tec.stt.bmk=2:159179,33:159179,34:159179,35:159179,36:159179,37:159179,38:159179,39:159179,40:159179,41:159179,42:159179,43:159179,44:159179,45:159179,46:159179,47:159179,48:159179,49:159179,50:159179,51:159179,52:159179,53:159179,54:159179,55:159179,";"std.tec.stt.bmk=56:159179,57:159179,58:159179,59:159179,60:159179,61:159179,62:159179,63:159179,64:159179,65:159179,66:159179,67:159179,68:159179,69:159179,70:159179,71:159179,72:159179,73:159179,74:159179,75:159179,76:159179,77:159179,78:159179,79:159179"})} -> Correlacao Mais recente 12 meses Em moeda orig ARX Vinson Adv Fc FIF RF Cred Priv - Resp Limitada | F1: {=_xll.ECONOMATICA(_xll.EcoRange(1,-5,26,-5),"Correlation","12M","LATEST",,,"ORIGINAL CURRENCY",,"false","true",,{"jtc.per=0";"std.tec.stt.bmk=0:53373,1:53373,2:53373,3:53373,4:53373,5:53373,6:53373,7:53373,8:53373,9:53373,10:53373,11:53373,12:53373,13:53373,14:53373,15:53373,16:53373,17:53373,18:53373,19:53373,20:53373,21:53373,22:53373,23:53373,24:53373,25:53373,26:5337";"std.tec.stt.bmk=3,27:53373,28:53373,29:53373,30:53373,31:53373,32:53373,33:53373,34:53373,35:53373,36:53373,37:53373,38:53373,39:53373,40:53373,41:53373,42:53373,43:53373,44:53373,45:53373,46:53373,47:53373,48:53373,49:53373,50:53373,51:53373,52:53373,53:";"std.tec.stt.bmk=53373,54:53373,55:53373,56:53373,57:53373,58:53373,59:53373,60:53373,61:53373,62:53373,63:53373,64:53373,65:53373,66:53373,67:53373,68:53373,69:53373,70:53373,71:53373,72:53373,73:53373,74:53373,75:53373,76:53373,77:53373,78:53373,79:53373"})} -> Correlacao Mais recente 12 meses Em moeda orig Capitânia Top Cred Priv Fc FIF RF - Resp Limitada | G1: {=_xll.ECONOMATICA(_xll.EcoRange(1,-6,26,-6),"Correlation","12M","LATEST",,,"ORIGINAL CURRENCY",,"false","true",,{"jtc.per=0";"std.tec.stt.bmk=0:173820,1:173820,2:173820,3:173820,4:173820,5:173820,6:173820,7:173820,";"std.tec.stt.bmk=8:173820,9:173820,10:173820,11:173820,12:173820,13:173820,14:173820,15:173820,16:173820,17:173820,18:173820,19:173820,20:173820,21:173820,22:173820,23:173820,24:173820,25:173820,26:173820,27:173820,28:173820,29:173820,30:173820,31:173820,3";"std.tec.stt.bmk=2:173820,33:173820,34:173820,35:173820,36:173820,37:173820,38:173820,39:173820,40:173820,41:173820,42:173820,43:173820,44:173820,45:173820,46:173820,47:173820,48:173820,49:173820,50:173820,51:173820,52:173820,53:173820,54:173820,55:173820,";"std.tec.stt.bmk=56:173820,57:173820,58:173820,59:173820,60:173820,61:173820,62:173820,63:173820,64:173820,65:173820,66:173820,67:173820,68:173820,69:173820,70:173820,71:173820,72:173820,73:173820,74:173820,75:173820,76:173820,77:173820,78:173820,79:173820"})} -> Correlacao Mais recente 12 meses Em moeda orig Classe Única de Cotas do Absolute Atenas Advisory FI Financeiro em Cota | H1: {=_xll.ECONOMATICA(_xll.EcoRange(1,-7,26,-7),"Correlation","12M","LATEST",,,"ORIGINAL CURRENCY",,"false","true",,{"jtc.per=0";"std.tec.stt.bmk=0:173821,1:173821,2:173821,3:173821,4:173821,5:173821,6:173821,7:173821,";"std.tec.stt.bmk=8:173821,9:173821,10:173821,11:173821,12:173821,13:173821,14:173821,15:173821,16:173821,17:173821,18:173821,19:173821,20:173821,21:173821,22:173821,23:173821,24:173821,25:173821,26:173821,27:173821,28:173821,29:173821,30:173821,31:173821,3";"std.tec.stt.bmk=2:173821,33:173821,34:173821,35:173821,36:173821,37:173821,38:173821,39:173821,40:173821,41:173821,42:173821,43:173821,44:173821,45:173821,46:173821,47:173821,48:173821,49:173821,50:173821,51:173821,52:173821,53:173821,54:173821,55:173821,";"std.tec.stt.bmk=56:173821,57:173821,58:173821,59:173821,60:173821,61:173821,62:173821,63:173821,64:173821,65:173821,66:173821,67:173821,68:173821,69:173821,70:173821,71:173821,72:173821,73:173821,74:173821,75:173821,76:173821,77:173821,78:173821,79:173821"})} -> Correlacao Mais recente 12 meses Em moeda orig Classe Única de Cotas do Absolute Creta Advisory F | I1: {=_xll.ECONOMATICA(_xll.EcoRange(1,-8,26,-8),"Correlation","12M","LATEST",,,"ORIGINAL CURRENCY",,"false","true",,{"jtc.per=0";"std.tec.stt.bmk=0:176480,1:176480,2:176480,3:176480,4:176480,5:176480,6:176480,7:176480,";"std.tec.stt.bmk=8:176480,9:176480,10:176480,11:176480,12:176480,13:176480,14:176480,15:176480,16:176480,17:176480,18:176480,19:176480,20:176480,21:176480,22:176480,23:176480,24:176480,25:176480,26:176480,27:176480,28:176480,29:176480,30:176480,31:176480,3";"std.tec.stt.bmk=2:176480,33:176480,34:176480,35:176480,36:176480,37:176480,38:176480,39:176480,40:176480,41:176480,42:176480,43:176480,44:176480,45:176480,46:176480,47:176480,48:176480,49:176480,50:176480,51:176480,52:176480,53:176480,54:176480,55:176480,";"std.tec.stt.bmk=56:176480,57:176480,58:176480,59:176480,60:176480,61:176480,62:176480,63:176480,64:176480,65:176480,66:176480,67:176480,68:176480,69:176480,70:176480,71:176480,72:176480,73:176480,74:176480,75:176480,76:176480,77:176480,78:176480,79:176480"})} -> Correlacao Mais recente 12 meses Em moeda orig Classe Única de Cotas do Absolute Olimpia Fundo de | J1: {=_xll.ECONOMATICA(_xll.EcoRange(1,-9,26,-9),"Correlation","12M","LATEST",,,"ORIGINAL CURRENCY",,"false","true",,{"jtc.per=0";"std.tec.stt.bmk=0:163596,1:163596,2:163596,3:163596,4:163596,5:163596,6:163596,7:163596,";"std.tec.stt.bmk=8:163596,9:163596,10:163596,11:163596,12:163596,13:163596,14:163596,15:163596,16:163596,17:163596,18:163596,19:163596,20:163596,21:163596,22:163596,23:163596,24:163596,25:163596,26:163596,27:163596,28:163596,29:163596,30:163596,31:163596,3";"std.tec.stt.bmk=2:163596,33:163596,34:163596,35:163596,36:163596,37:163596,38:163596,39:163596,40:163596,41:163596,42:163596,43:163596,44:163596,45:163596,46:163596,47:163596,48:163596,49:163596,50:163596,51:163596,52:163596,53:163596,54:163596,55:163596,";"std.tec.stt.bmk=56:163596,57:163596,58:163596,59:163596,60:163596,61:163596,62:163596,63:163596,64:163596,65:163596,66:163596,67:163596,68:163596,69:163596,70:163596,71:163596,72:163596,73:163596,74:163596,75:163596,76:163596,77:163596,78:163596,79:163596"})} -> Correlacao Mais recente 12 meses Em moeda orig Classe Unica de Cotas do Af Horizonte Fundo de Inv | K1: {=_xll.ECONOMATICA(_xll.EcoRange(1,-10,26,-10),"Correlation","12M","LATEST",,,"ORIGINAL CURRENCY",,"false","true",,{"jtc.per=0";"std.tec.stt.bmk=0:100360,1:100360,2:100360,3:100360,4:100360,5:100360,6:100360,7:100360,";"std.tec.stt.bmk=8:100360,9:100360,10:100360,11:100360,12:100360,13:100360,14:100360,15:100360,16:100360,17:100360,18:100360,19:100360,20:100360,21:100360,22:100360,23:100360,24:100360,25:100360,26:100360,27:100360,28:100360,29:100360,30:100360,31:100360,3";"std.tec.stt.bmk=2:100360,33:100360,34:100360,35:100360,36:100360,37:100360,38:100360,39:100360,40:100360,41:100360,42:100360,43:100360,44:100360,45:100360,46:100360,47:100360,48:100360,49:100360,50:100360,51:100360,52:100360,53:100360,54:100360,55:100360,";"std.tec.stt.bmk=56:100360,57:100360,58:100360,59:100360,60:100360,61:100360,62:100360,63:100360,64:100360,65:100360,66:100360,67:100360,68:100360,69:100360,70:100360,71:100360,72:100360,73:100360,74:100360,75:100360,76:100360,77:100360,78:100360,79:100360"})} -> Correlacao Mais recente 12 meses Em moeda orig Classe Única de Cotas do Af Invest Geraes 30 FI Financeiro RF - | L1: {=_xll.ECONOMATICA(_xll.EcoRange(1,-11,26,-11),"Correlation","12M","LATEST",,,"ORIGINAL CURRENCY",,"false","true",,{"jtc.per=0";"std.tec.stt.bmk=0:41748,1:41748,2:41748,3:41748,4:41748,5:41748,6:41748,7:41748,8:41748,9:41748,10:41748,11:41748,12:41748,13:41748,14:41748,15:41748,16:41748,17:41748,18:41748,19:41748,20:41748,21:41748,22:41748,23:41748,24:41748,25:41748,26:4174";"std.tec.stt.bmk=8,27:41748,28:41748,29:41748,30:41748,31:41748,32:41748,33:41748,34:41748,35:41748,36:41748,37:41748,38:41748,39:41748,40:41748,41:41748,42:41748,43:41748,44:41748,45:41748,46:41748,47:41748,48:41748,49:41748,50:41748,51:41748,52:41748,53:";"std.tec.stt.bmk=41748,54:41748,55:41748,56:41748,57:41748,58:41748,59:41748,60:41748,61:41748,62:41748,63:41748,64:41748,65:41748,66:41748,67:41748,68:41748,69:41748,70:41748,71:41748,72:41748,73:41748,74:41748,75:41748,76:41748,77:41748,78:41748,79:41748"})} -> Correlacao Mais recente 12 meses Em moeda orig Classe Única de Cotas do Af Invest Geraes FI Financeiro RF - Cr | M1: {=_xll.ECONOMATICA(_xll.EcoRange(1,-12,26,-12),"Correlation","12M","LATEST",,,"ORIGINAL CURRENCY",,"false","true",,{"jtc.per=0";"std.tec.stt.bmk=0:139069,1:139069,2:139069,3:139069,4:139069,5:139069,6:139069,7:139069,";"std.tec.stt.bmk=8:139069,9:139069,10:139069,11:139069,12:139069,13:139069,14:139069,15:139069,16:139069,17:139069,18:139069,19:139069,20:139069,21:139069,22:139069,23:139069,24:139069,25:139069,26:139069,27:139069,28:139069,29:139069,30:139069,31:139069,3";"std.tec.stt.bmk=2:139069,33:139069,34:139069,35:139069,36:139069,37:139069,38:139069,39:139069,40:139069,41:139069,42:139069,43:139069,44:139069,45:139069,46:139069,47:139069,48:139069,49:139069,50:139069,51:139069,52:139069,53:139069,54:139069,55:139069,";"std.tec.stt.bmk=56:139069,57:139069,58:139069,59:139069,60:139069,61:139069,62:139069,63:139069,64:139069,65:139069,66:139069,67:139069,68:139069,69:139069,70:139069,71:139069,72:139069,73:139069,74:139069,75:139069,76:139069,77:139069,78:139069,79:139069"})} -> Correlacao Mais recente 12 meses Em moeda orig Classe Única de Cotas do Riza Lotus Fundo de Inves | N1: {=_xll.ECONOMATICA(_xll.EcoRange(1,-13,26,-13),"Correlation","12M","LATEST",,,"ORIGINAL CURRENCY",,"false","true",,{"jtc.per=0";"std.tec.stt.bmk=0:162953,1:162953,2:162953,3:162953,4:162953,5:162953,6:162953,7:162953,";"std.tec.stt.bmk=8:162953,9:162953,10:162953,11:162953,12:162953,13:162953,14:162953,15:162953,16:162953,17:162953,18:162953,19:162953,20:162953,21:162953,22:162953,23:162953,24:162953,25:162953,26:162953,27:162953,28:162953,29:162953,30:162953,31:162953,3";"std.tec.stt.bmk=2:162953,33:162953,34:162953,35:162953,36:162953,37:162953,38:162953,39:162953,40:162953,41:162953,42:162953,43:162953,44:162953,45:162953,46:162953,47:162953,48:162953,49:162953,50:162953,51:162953,52:162953,53:162953,54:162953,55:162953,";"std.tec.stt.bmk=56:162953,57:162953,58:162953,59:162953,60:162953,61:162953,62:162953,63:162953,64:162953,65:162953,66:162953,67:162953,68:162953,69:162953,70:162953,71:162953,72:162953,73:162953,74:162953,75:162953,76:162953,77:162953,78:162953,79:162953"})} -> Correlacao Mais recente 12 meses Em moeda orig Classe Única de Cotas do Riza Lotus Plus Advisory | O1: {=_xll.ECONOMATICA(_xll.EcoRange(1,-14,26,-14),"Correlation","12M","LATEST",,,"ORIGINAL CURRENCY",,"false","true",,{"jtc.per=0";"std.tec.stt.bmk=0:108665,1:108665,2:108665,3:108665,4:108665,5:108665,6:108665,7:108665,";"std.tec.stt.bmk=8:108665,9:108665,10:108665,11:108665,12:108665,13:108665,14:108665,15:108665,16:108665,17:108665,18:108665,19:108665,20:108665,21:108665,22:108665,23:108665,24:108665,25:108665,26:108665,27:108665,28:108665,29:108665,30:108665,31:108665,3";"std.tec.stt.bmk=2:108665,33:108665,34:108665,35:108665,36:108665,37:108665,38:108665,39:108665,40:108665,41:108665,42:108665,43:108665,44:108665,45:108665,46:108665,47:108665,48:108665,49:108665,50:108665,51:108665,52:108665,53:108665,54:108665,55:108665,";"std.tec.stt.bmk=56:108665,57:108665,58:108665,59:108665,60:108665,61:108665,62:108665,63:108665,64:108665,65:108665,66:108665,67:108665,68:108665,69:108665,70:108665,71:108665,72:108665,73:108665,74:108665,75:108665,76:108665,77:108665,78:108665,79:108665"})} -> Correlacao Mais recente 12 meses Em moeda orig Classe Única do Western Asset Total Credit Advisory FIC de Fund | P1: {=_xll.ECONOMATICA(_xll.EcoRange(1,-15,26,-15),"Correlation","12M","LATEST",,,"ORIGINAL CURRENCY",,"false","true",,{"jtc.per=0";"std.tec.stt.bmk=0:102928,1:102928,2:102928,3:102928,4:102928,5:102928,6:102928,7:102928,";"std.tec.stt.bmk=8:102928,9:102928,10:102928,11:102928,12:102928,13:102928,14:102928,15:102928,16:102928,17:102928,18:102928,19:102928,20:102928,21:102928,22:102928,23:102928,24:102928,25:102928,26:102928,27:102928,28:102928,29:102928,30:102928,31:102928,3";"std.tec.stt.bmk=2:102928,33:102928,34:102928,35:102928,36:102928,37:102928,38:102928,39:102928,40:102928,41:102928,42:102928,43:102928,44:102928,45:102928,46:102928,47:102928,48:102928,49:102928,50:102928,51:102928,52:102928,53:102928,54:102928,55:102928,";"std.tec.stt.bmk=56:102928,57:102928,58:102928,59:102928,60:102928,61:102928,62:102928,63:102928,64:102928,65:102928,66:102928,67:102928,68:102928,69:102928,70:102928,71:102928,72:102928,73:102928,74:102928,75:102928,76:102928,77:102928,78:102928,79:102928"})} -> Correlacao Mais recente 12 meses Em moeda orig Daycoval Classic 30 Classe de Investimento RF Cred Priv Resp Limitada | Q1: {=_xll.ECONOMATICA(_xll.EcoRange(1,-16,26,-16),"Correlation","12M","LATEST",,,"ORIGINAL CURRENCY",,"false","true",,{"jtc.per=0";"std.tec.stt.bmk=0:48273,1:48273,2:48273,3:48273,4:48273,5:48273,6:48273,7:48273,8:48273,9:48273,10:48273,11:48273,12:48273,13:48273,14:48273,15:48273,16:48273,17:48273,18:48273,19:48273,20:48273,21:48273,22:48273,23:48273,24:48273,25:48273,26:4827";"std.tec.stt.bmk=3,27:48273,28:48273,29:48273,30:48273,31:48273,32:48273,33:48273,34:48273,35:48273,36:48273,37:48273,38:48273,39:48273,40:48273,41:48273,42:48273,43:48273,44:48273,45:48273,46:48273,47:48273,48:48273,49:48273,50:48273,51:48273,52:48273,53:";"std.tec.stt.bmk=48273,54:48273,55:48273,56:48273,57:48273,58:48273,59:48273,60:48273,61:48273,62:48273,63:48273,64:48273,65:48273,66:48273,67:48273,68:48273,69:48273,70:48273,71:48273,72:48273,73:48273,74:48273,75:48273,76:48273,77:48273,78:48273,79:48273"})} -> Correlacao Mais recente 12 meses Em moeda orig Daycoval Classic Classe de Investimento em Cotas de FI RF Cred Priv Resp Limitadýs C_x0018_ ¬ý | R1: {=_xll.ECONOMATICA(_xll.EcoRange(1,-17,26,-17),"Correlation","12M","LATEST",,,"ORIGINAL CURRENCY",,"false","true",,{"jtc.per=0";"std.tec.stt.bmk=0:72394,1:72394,2:72394,3:72394,4:72394,5:72394,6:72394,7:72394,8:72394,9:72394,10:72394,11:72394,12:72394,13:72394,14:72394,15:72394,16:72394,17:72394,18:72394,19:72394,20:72394,21:72394,22:72394,23:72394,24:72394,25:72394,26:7239";"std.tec.stt.bmk=4,27:72394,28:72394,29:72394,30:72394,31:72394,32:72394,33:72394,34:72394,35:72394,36:72394,37:72394,38:72394,39:72394,40:72394,41:72394,42:72394,43:72394,44:72394,45:72394,46:72394,47:72394,48:72394,49:72394,50:72394,51:72394,52:72394,53:";"std.tec.stt.bmk=72394,54:72394,55:72394,56:72394,57:72394,58:72394,59:72394,60:72394,61:72394,62:72394,63:72394,64:72394,65:72394,66:72394,67:72394,68:72394,69:72394,70:72394,71:72394,72:72394,73:72394,74:72394,75:72394,76:72394,77:72394,78:72394,79:72394"})} -> Correlacao Mais recente 12 meses Em moeda orig Inter Conservador FI Financeiro RF Cred Priv Responsabili | S1: {=_xll.ECONOMATICA(_xll.EcoRange(1,-18,26,-18),"Correlation","12M","LATEST",,,"ORIGINAL CURRENCY",,"false","true",,{"jtc.per=0";"std.tec.stt.bmk=0:98107,1:98107,2:98107,3:98107,4:98107,5:98107,6:98107,7:98107,8:98107,9:98107,10:98107,11:98107,12:98107,13:98107,14:98107,15:98107,16:98107,17:98107,18:98107,19:98107,20:98107,21:98107,22:98107,23:98107,24:98107,25:98107,26:9810";"std.tec.stt.bmk=7,27:98107,28:98107,29:98107,30:98107,31:98107,32:98107,33:98107,34:98107,35:98107,36:98107,37:98107,38:98107,39:98107,40:98107,41:98107,42:98107,43:98107,44:98107,45:98107,46:98107,47:98107,48:98107,49:98107,50:98107,51:98107,52:98107,53:";"std.tec.stt.bmk=98107,54:98107,55:98107,56:98107,57:98107,58:98107,59:98107,60:98107,61:98107,62:98107,63:98107,64:98107,65:98107,66:98107,67:98107,68:98107,69:98107,70:98107,71:98107,72:98107,73:98107,74:98107,75:98107,76:98107,77:98107,78:98107,79:98107"})} -> Correlacao Mais recente 12 meses Em moeda orig Iridium Apollo Fc FIF RF Cred Priv LP - Resp Limitada | T1: {=_xll.ECONOMATICA(_xll.EcoRange(1,-19,26,-19),"Correlation","12M","LATEST",,,"ORIGINAL CURRENCY",,"false","true",,{"jtc.per=0";"std.tec.stt.bmk=0:116975,1:116975,2:116975,3:116975,4:116975,5:116975,6:116975,7:116975,";"std.tec.stt.bmk=8:116975,9:116975,10:116975,11:116975,12:116975,13:116975,14:116975,15:116975,16:116975,17:116975,18:116975,19:116975,20:116975,21:116975,22:116975,23:116975,24:116975,25:116975,26:116975,27:116975,28:116975,29:116975,30:116975,31:116975,3";"std.tec.stt.bmk=2:116975,33:116975,34:116975,35:116975,36:116975,37:116975,38:116975,39:116975,40:116975,41:116975,42:116975,43:116975,44:116975,45:116975,46:116975,47:116975,48:116975,49:116975,50:116975,51:116975,52:116975,53:116975,54:116975,55:116975,";"std.tec.stt.bmk=56:116975,57:116975,58:116975,59:116975,60:116975,61:116975,62:116975,63:116975,64:116975,65:116975,66:116975,67:116975,68:116975,69:116975,70:116975,71:116975,72:116975,73:116975,74:116975,75:116975,76:116975,77:116975,78:116975,79:116975"})} -> Correlacao Mais recente 12 meses Em moeda orig Iridium Titan Advisory Fc FIF RF Cred Priv ? Resp Limitada | U1: {=_xll.ECONOMATICA(_xll.EcoRange(1,-20,26,-20),"Correlation","12M","LATEST",,,"ORIGINAL CURRENCY",,"false","true",,{"jtc.per=0";"std.tec.stt.bmk=0:74380,1:74380,2:74380,3:74380,4:74380,5:74380,6:74380,7:74380,8:74380,9:74380,10:74380,11:74380,12:74380,13:74380,14:74380,15:74380,16:74380,17:74380,18:74380,19:74380,20:74380,21:74380,22:74380,23:74380,24:74380,25:74380,26:7438";"std.tec.stt.bmk=0,27:74380,28:74380,29:74380,30:74380,31:74380,32:74380,33:74380,34:74380,35:74380,36:74380,37:74380,38:74380,39:74380,40:74380,41:74380,42:74380,43:74380,44:74380,45:74380,46:74380,47:74380,48:74380,49:74380,50:74380,51:74380,52:74380,53:";"std.tec.stt.bmk=74380,54:74380,55:74380,56:74380,57:74380,58:74380,59:74380,60:74380,61:74380,62:74380,63:74380,64:74380,65:74380,66:74380,67:74380,68:74380,69:74380,70:74380,71:74380,72:74380,73:74380,74:74380,75:74380,76:74380,77:74380,78:74380,79:74380"})} -> Correlacao Mais recente 12 meses Em moeda orig Jgp Select Fc FIF Mult Cred Priv - Resp Limitada | V1: {=_xll.ECONOMATICA(_xll.EcoRange(1,-21,26,-21),"Correlation","12M","LATEST",,,"ORIGINAL CURRENCY",,"false","true",,{"jtc.per=0";"std.tec.stt.bmk=0:164961,1:164961,2:164961,3:164961,4:164961,5:164961,6:164961,7:164961,";"std.tec.stt.bmk=8:164961,9:164961,10:164961,11:164961,12:164961,13:164961,14:164961,15:164961,16:164961,17:164961,18:164961,19:164961,20:164961,21:164961,22:164961,23:164961,24:164961,25:164961,26:164961,27:164961,28:164961,29:164961,30:164961,31:164961,3";"std.tec.stt.bmk=2:164961,33:164961,34:164961,35:164961,36:164961,37:164961,38:164961,39:164961,40:164961,41:164961,42:164961,43:164961,44:164961,45:164961,46:164961,47:164961,48:164961,49:164961,50:164961,51:164961,52:164961,53:164961,54:164961,55:164961,";"std.tec.stt.bmk=56:164961,57:164961,58:164961,59:164961,60:164961,61:164961,62:164961,63:164961,64:164961,65:164961,66:164961,67:164961,68:164961,69:164961,70:164961,71:164961,72:164961,73:164961,74:164961,75:164961,76:164961,77:164961,78:164961,79:164961"})} -> Correlacao Mais recente 12 meses Em moeda orig Nu Reserva Imediata FIF Cic RF Ref DI Resp Limitad | W1: {=_xll.ECONOMATICA(_xll.EcoRange(1,-22,26,-22),"Correlation","12M","LATEST",,,"ORIGINAL CURRENCY",,"false","true",,{"jtc.per=0";"std.tec.stt.bmk=0:104803,1:104803,2:104803,3:104803,4:104803,5:104803,6:104803,7:104803,";"std.tec.stt.bmk=8:104803,9:104803,10:104803,11:104803,12:104803,13:104803,14:104803,15:104803,16:104803,17:104803,18:104803,19:104803,20:104803,21:104803,22:104803,23:104803,24:104803,25:104803,26:104803,27:104803,28:104803,29:104803,30:104803,31:104803,3";"std.tec.stt.bmk=2:104803,33:104803,34:104803,35:104803,36:104803,37:104803,38:104803,39:104803,40:104803,41:104803,42:104803,43:104803,44:104803,45:104803,46:104803,47:104803,48:104803,49:104803,50:104803,51:104803,52:104803,53:104803,54:104803,55:104803,";"std.tec.stt.bmk=56:104803,57:104803,58:104803,59:104803,60:104803,61:104803,62:104803,63:104803,64:104803,65:104803,66:104803,67:104803,68:104803,69:104803,70:104803,71:104803,72:104803,73:104803,74:104803,75:104803,76:104803,77:104803,78:104803,79:104803"})} -> Correlacao Mais recente 12 meses Em moeda orig Polo Crédito Corporativo Advisory Fc FIF RF Cred Priv LP - Resp Limitada | X1: {=_xll.ECONOMATICA(_xll.EcoRange(1,-23,26,-23),"Correlation","12M","LATEST",,,"ORIGINAL CURRENCY",,"false","true",,{"jtc.per=0";"std.tec.stt.bmk=0:81989,1:81989,2:81989,3:81989,4:81989,5:81989,6:81989,7:81989,8:81989,9:81989,10:81989,11:81989,12:81989,13:81989,14:81989,15:81989,16:81989,17:81989,18:81989,19:81989,20:81989,21:81989,22:81989,23:81989,24:81989,25:81989,26:8198";"std.tec.stt.bmk=9,27:81989,28:81989,29:81989,30:81989,31:81989,32:81989,33:81989,34:81989,35:81989,36:81989,37:81989,38:81989,39:81989,40:81989,41:81989,42:81989,43:81989,44:81989,45:81989,46:81989,47:81989,48:81989,49:81989,50:81989,51:81989,52:81989,53:";"std.tec.stt.bmk=81989,54:81989,55:81989,56:81989,57:81989,58:81989,59:81989,60:81989,61:81989,62:81989,63:81989,64:81989,65:81989,66:81989,67:81989,68:81989,69:81989,70:81989,71:81989,72:81989,73:81989,74:81989,75:81989,76:81989,77:81989,78:81989,79:81989"})} -> Correlacao Mais recente 12 meses Em moeda orig Polo Total Credit Fc FIF Mult Cred Priv - Resp Limitada | Y1: {=_xll.ECONOMATICA(_xll.EcoRange(1,-24,26,-24),"Correlation","12M","LATEST",,,"ORIGINAL CURRENCY",,"false","true",,{"jtc.per=0";"std.tec.stt.bmk=0:65346,1:65346,2:65346,3:65346,4:65346,5:65346,6:65346,7:65346,8:65346,9:65346,10:65346,11:65346,12:65346,13:65346,14:65346,15:65346,16:65346,17:65346,18:65346,19:65346,20:65346,21:65346,22:65346,23:65346,24:65346,25:65346,26:6534";"std.tec.stt.bmk=6,27:65346,28:65346,29:65346,30:65346,31:65346,32:65346,33:65346,34:65346,35:65346,36:65346,37:65346,38:65346,39:65346,40:65346,41:65346,42:65346,43:65346,44:65346,45:65346,46:65346,47:65346,48:65346,49:65346,50:65346,51:65346,52:65346,53:";"std.tec.stt.bmk=65346,54:65346,55:65346,56:65346,57:65346,58:65346,59:65346,60:65346,61:65346,62:65346,63:65346,64:65346,65:65346,66:65346,67:65346,68:65346,69:65346,70:65346,71:65346,72:65346,73:65346,74:65346,75:65346,76:65346,77:65346,78:65346,79:65346"})} -> Correlacao Mais recente 12 meses Em moeda orig Porto Seguro FIF RF Ref DI Créd Priv Resp Limitada | Z1: {=_xll.ECONOMATICA(_xll.EcoRange(1,-25,26,-25),"Correlation","12M","LATEST",,,"ORIGINAL CURRENCY",,"false","true",,{"jtc.per=0";"std.tec.stt.bmk=0:132231,1:132231,2:132231,3:132231,4:132231,5:132231,6:132231,7:132231,";"std.tec.stt.bmk=8:132231,9:132231,10:132231,11:132231,12:132231,13:132231,14:132231,15:132231,16:132231,17:132231,18:132231,19:132231,20:132231,21:132231,22:132231,23:132231,24:132231,25:132231,26:132231,27:132231,28:132231,29:132231,30:132231,31:132231,3";"std.tec.stt.bmk=2:132231,33:132231,34:132231,35:132231,36:132231,37:132231,38:132231,39:132231,40:132231,41:132231,42:132231,43:132231,44:132231,45:132231,46:132231,47:132231,48:132231,49:132231,50:132231,51:132231,52:132231,53:132231,54:132231,55:132231,";"std.tec.stt.bmk=56:132231,57:132231,58:132231,59:132231,60:132231,61:132231,62:132231,63:132231,64:132231,65:132231,66:132231,67:132231,68:132231,69:132231,70:132231,71:132231,72:132231,73:132231,74:132231,75:132231,76:132231,77:132231,78:132231,79:132231"})} -> Correlacao Mais recente 12 meses Em moeda orig Porto Seguro Ipê FIF da Cic RF Créd Priv LP Resp Limitada | AA1: {=_xll.ECONOMATICA(_xll.EcoRange(1,-26,26,-26),"Correlation","12M","LATEST",,,"ORIGINAL CURRENCY",,"false","true",,{"jtc.per=0";"std.tec.stt.bmk=0:117256,1:117256,2:117256,3:117256,4:117256,5:117256,6:117256,7:117256,";"std.tec.stt.bmk=8:117256,9:117256,10:117256,11:117256,12:117256,13:117256,14:117256,15:117256,16:117256,17:117256,18:117256,19:117256,20:117256,21:117256,22:117256,23:117256,24:117256,25:117256,26:117256,27:117256,28:117256,29:117256,30:117256,31:117256,3";"std.tec.stt.bmk=2:117256,33:117256,34:117256,35:117256,36:117256,37:117256,38:117256,39:117256,40:117256,41:117256,42:117256,43:117256,44:117256,45:117256,46:117256,47:117256,48:117256,49:117256,50:117256,51:117256,52:117256,53:117256,54:117256,55:117256,";"std.tec.stt.bmk=56:117256,57:117256,58:117256,59:117256,60:117256,61:117256,62:117256,63:117256,64:117256,65:117256,66:117256,67:117256,68:117256,69:117256,70:117256,71:117256,72:117256,73:117256,74:117256,75:117256,76:117256,77:117256,78:117256,79:117256"})} -> Correlacao Mais recente 12 meses Em moeda orig Sparta Max Advisory Fc FIF RF Cred Priv LP - Resp Limitada | AB1: {=_xll.ECONOMATICA(_xll.EcoRange(1,-27,26,-27),"Correlation","12M","LATEST",,,"ORIGINAL CURRENCY",,"false","true",,{"jtc.per=0";"std.tec.stt.bmk=0:116980,1:116980,2:116980,3:116980,4:116980,5:116980,6:116980,7:116980,";"std.tec.stt.bmk=8:116980,9:116980,10:116980,11:116980,12:116980,13:116980,14:116980,15:116980,16:116980,17:116980,18:116980,19:116980,20:116980,21:116980,22:116980,23:116980,24:116980,25:116980,26:116980,27:116980,28:116980,29:116980,30:116980,31:116980,3";"std.tec.stt.bmk=2:116980,33:116980,34:116980,35:116980,36:116980,37:116980,38:116980,39:116980,40:116980,41:116980,42:116980,43:116980,44:116980,45:116980,46:116980,47:116980,48:116980,49:116980,50:116980,51:116980,52:116980,53:116980,54:116980,55:116980,";"std.tec.stt.bmk=56:116980,57:116980,58:116980,59:116980,60:116980,61:116980,62:116980,63:116980,64:116980,65:116980,66:116980,67:116980,68:116980,69:116980,70:116980,71:116980,72:116980,73:116980,74:116980,75:116980,76:116980,77:116980,78:116980,79:116980"})} -> Correlacao Mais recente 12 meses Em moeda orig Sparta Top Adv Fc FI RF Cred Priv LP - Resp Limitada
A2: 634468<BraNa> | B2: ARX Denali Advisory Fc FIF RF Créd Priv - Resp Lim | C2: 1 | D2: 0.80660057 | E2: 0.86557442 | F2: 0.30936013 | G2: 0.11717329 | H2: 0.17470048 | I2: 0.1226426 | J2: 0.051435473 | K2: 0.083672675 | L2: 0.083464113 | M2: 0.075141071 | N2: 0.022642024 | O2: 0.32688934 | P2: 0.088196584 | Q2: 0.23920471 | R2: 0.50019884 | S2: 0.51505892 | T2: 0.4301403 | U2: 0.17575852 | V2: 0.0072928153 | W2: 0.39378254 | X2: 0.11839405 | Y2: 0.20445602 | Z2: 0.45339477 | AA2: 0.033804048 | AB2: 0.070134819
A3: 526886<BraNa> | B3: ARX Everest Advisory Fc FIF RF Cred Priv - Resp Limitada | C3: 0.80660057 | D3: 1 | E3: 0.91799651 | F3: 0.24077845 | G3: 0.033221823 | H3: 0.057506898 | I3: -0.046931959 | J3: 0.0065493193 | K3: 0.050991617 | L3: 0.028904916 | M3: -0.0053501093 | N3: -0.034782462 | O3: 0.17140829 | P3: -0.0053974841 | Q3: 0.077612614 | R3: 0.47335686 | S3: 0.50058456 | T3: 0.40873459 | U3: 0.16978914 | V3: 0.011630725 | W3: 0.27210004 | X3: 0.075436954 | Y3: 0.086732905 | Z3: 0.26450099 | AA3: 0.078810478 | AB3: 0.09451381
A4: 601462<BraNa> | B4: ARX Vinson Adv Fc FIF RF Cred Priv - Resp Limitada | C4: 0.86557442 | D4: 0.91799651 | E4: 1 | F4: 0.22598785 | G4: 0.087303385 | H4: 0.13279623 | I4: 0.031033905 | J4: 0.055816487 | K4: 0.094052928 | L4: 0.077938592 | M4: 0.056631131 | N4: 0.013461238 | O4: 0.25749886 | P4: 0.088512402 | Q4: 0.20887011 | R4: 0.56056085 | S4: 0.59265757 | T4: 0.45771662 | U4: 0.21653841 | V4: 0.023705388 | W4: 0.3908108 | X4: 0.12331971 | Y4: 0.15865223 | Z4: 0.37896234 | AA4: 0.10369879 | AB4: 0.12203094
A5: 284491<BraNa> | B5: Capitânia Top Cred Priv Fc FIF RF - Resp Limitada | C5: 0.30936013 | D5: 0.24077845 | E5: 0.22598785 | F5: 1 | G5: -0.0038735133 | H5: -0.00088875867 | I5: 0.007610546 | J5: 0.23137622 | K5: 0.15293293 | L5: 0.23417922 | M5: 0.038473756 | N5: 0.065765607 | O5: 0.073117675 | P5: -0.05121892 | Q5: -0.055498658 | R5: 0.27937983 | S5: 0.34516234 | T5: 0.25347103 | U5: 0.053381603 | V5: -0.099549415 | W5: 0.12530841 | X5: 0.16967605 | Y5: -0.010955786 | Z5: 0.014054261 | AA5: 0.066692587 | AB5: 0.045666972
A6: 677930<BraNa> | B6: Classe Única de Cotas do Absolute Atenas Advisory FI Financeiro em Cota | C6: 0.11717329 | D6: 0.033221823 | E6: 0.087303385 | F6: -0.0038735133 | G6: 1 | H6: 0.94246151 | I6: 0.59634361 | J6: 0.077544848 | K6: 0.046949027 | L6: 0.063685688 | M6: 0.041976162 | N6: 0.015833454 | O6: 0.17882174 | P6: 0.19937568 | Q6: 0.27767778 | R6: 0.028529202 | S6: -0.010509668 | T6: 0.0037812622 | U6: 0.029056015 | V6: 0.016275949 | W6: 0.24212751 | X6: 0.14333459 | Y6: 0.095733955 | Z6: 0.20044785 | AA6: 0.14869539 | AB6: 0.16134596
A7: 678007<BraNa> | B7: Classe Única de Cotas do Absolute Creta Advisory F | C7: 0.17470048 | D7: 0.057506898 | E7: 0.13279623 | F7: -0.00088875867 | G7: 0.94246151 | H7: 1 | I7: 0.65863419 | J7: 0.086211791 | K7: 0.050288899 | L7: 0.070308478 | M7: 0.10417812 | N7: 0.053055291 | O7: 0.22242581 | P7: 0.25964194 | Q7: 0.39680987 | R7: 0.076313204 | S7: 0.0065975506 | T7: 0.012833406 | U7: 0.080108526 | V7: 0.04836853 | W7: 0.33680343 | X7: 0.14660268 | Y7: 0.15074793 | Z7: 0.31264152 | AA7: 0.17875397 | AB7: 0.20076021
A8: 687138<BraNa> | B8: Classe Única de Cotas do Absolute Olimpia Fundo de | C8: 0.1226426 | D8: -0.046931959 | E8: 0.031033905 | F8: 0.007610546 | G8: 0.59634361 | H8: 0.65863419 | I8: 1 | J8: 0.11890789 | K8: 0.059485705 | L8: 0.088274223 | M8: 0.17465304 | N8: 0.12239907 | O8: 0.27183204 | P8: 0.17326414 | Q8: 0.34859838 | R8: 0.014365083 | S8: -0.011091878 | T8: -0.0035955122 | U8: 0.15009889 | V8: -0.01203619 | W8: 0.26398323 | X8: 0.19281638 | Y8: 0.058234003 | Z8: 0.22021472 | AA8: 0.13707994 | AB8: 0.1534743
A9: 624977<BraNa> | B9: Classe Unica de Cotas do Af Horizonte Fundo de Inv | C9: 0.051435473 | D9: 0.0065493193 | E9: 0.055816487 | F9: 0.23137622 | G9: 0.077544848 | H9: 0.086211791 | I9: 0.11890789 | J9: 1 | K9: 0.6866213 | L9: 0.77396937 | M9: 0.090689796 | N9: 0.071674814 | O9: 0.12259399 | P9: 0.16671512 | Q9: 0.1673804 | R9: 0.049055473 | S9: 0.20334097 | T9: 0.23302661 | U9: 0.18786725 | V9: 0.052228882 | W9: 0.17152563 | X9: 0.11871626 | Y9: 0.098063345 | Z9: 0.18263271 | AA9: 0.17371536 | AB9: 0.18780982
A10: 462276<BraNa> | B10: Classe Única de Cotas do Af Invest Geraes 30 FI Financeiro RF - | C10: 0.083672675 | D10: 0.050991617 | E10: 0.094052928 | F10: 0.15293293 | G10: 0.046949027 | H10: 0.050288899 | I10: 0.059485705 | J10: 0.6866213 | K10: 1 | L10: 0.94366056 | M10: 0.091189788 | N10: 0.068676439 | O10: 0.18845283 | P10: 0.069357864 | Q10: 0.10381083 | R10: 0.083848518 | S10: 0.18097875 | T10: 0.24790339 | U10: 0.26250909 | V10: 0.058602527 | W10: 0.15218254 | X10: 0.14895776 | Y10: -0.0084262847 | Z10: 0.063675284 | AA10: 0.23359119 | AB10: 0.2554295
A11: 216658<BraNa> | B11: Classe Única de Cotas do Af Invest Geraes FI Financeiro RF - Cr | C11: 0.083464113 | D11: 0.028904916 | E11: 0.077938592 | F11: 0.23417922 | G11: 0.063685688 | H11: 0.070308478 | I11: 0.088274223 | J11: 0.77396937 | K11: 0.94366056 | L11: 1 | M11: 0.1291822 | N11: 0.093933599 | O11: 0.19655994 | P11: 0.11817354 | Q11: 0.13882349 | R11: 0.098933465 | S11: 0.24069294 | T11: 0.28042962 | U11: 0.23842802 | V11: 0.06551028 | W11: 0.15309493 | X11: 0.18033062 | Y11: 0.010084241 | Z11: 0.081270126 | AA11: 0.23218611 | AB11: 0.25207875
A12: 531553<BraNa> | B12: Classe Única de Cotas do Riza Lotus Fundo de Inves | C12: 0.075141071 | D12: -0.0053501093 | E12: 0.056631131 | F12: 0.038473756 | G12: 0.041976162 | H12: 0.10417812 | I12: 0.17465304 | J12: 0.090689796 | K12: 0.091189788 | L12: 0.1291822 | M12: 1 | N12: 0.92255091 | O12: 0.066690867 | P12: 0.27219034 | Q12: 0.23894355 | R12: 0.12529229 | S12: 0.059903749 | T12: 0.038011829 | U12: 0.13015922 | V12: 0.066638733 | W12: 0.1128139 | X12: 0.090664247 | Y12: 0.036571077 | Z12: 0.11008855 | AA12: 0.14561894 | AB12: 0.17452378
A13: 620955<BraNa> | B13: Classe Única de Cotas do Riza Lotus Plus Advisory | C13: 0.022642024 | D13: -0.034782462 | E13: 0.013461238 | F13: 0.065765607 | G13: 0.015833454 | H13: 0.053055291 | I13: 0.12239907 | J13: 0.071674814 | K13: 0.068676439 | L13: 0.093933599 | M13: 0.92255091 | N13: 1 | O13: -0.023151257 | P13: 0.21772654 | Q13: 0.14851733 | R13: 0.07544737 | S13: 0.026872265 | T13: 0.0083195727 | U13: 0.057039198 | V13: 0.055718199 | W13: 0.056531409 | X13: 0.061709624 | Y13: 0.013282562 | Z13: 0.094375039 | AA13: 0.10306147 | AB13: 0.11686734
... A27: 494089<BraNa> | B27: Sparta Top Adv Fc FI RF Cred Priv LP - Resp Limitada | C27: 0.070134819 | D27: 0.09451381 | E27: 0.12203094 | F27: 0.045666972 | G27: 0.16134596 | H27: 0.20076021 | I27: 0.1534743 | J27: 0.18780982 | K27: 0.2554295 | L27: 0.25207875 | M27: 0.17452378 | N27: 0.11686734 | O27: 0.13540432 | P27: 0.2453724 | Q27: 0.24409376 | R27: 0.11267343 | S27: 0.059355988 | T27: 0.060457225 | U27: 0.62146801 | V27: 0.16580145 | W27: 0.21658371 | X27: 0.12568007 | Y27: 0.13038195 | Z27: 0.20199144 | AA27: 0.8788742 | AB27: 1

Sheet Correlação código
B1: ARX Denali | C1: ARX Everest Advisory | D1: ARX Vinson Advisory | E1: Capitânia Top | F1: Absolute Atenas | G1: Absolute Creta | H1: Absolute Olimpia | I1: Horizonte | J1: Geraes 30 | K1: GERAES | L1: Riza Lotus | M1: Riza Lotus Plus | N1: Western Asset Total | O1: Daycoval Classic 30 | P1: Daycoval Classic | Q1: Inter Conservador | R1: Iridium Apollo | S1: Iridium Titan Advisory | T1: JGP Select | U1: Nu Reserva Imediata | V1: Polo Crédito Corporativo | W1: Polo Total | X1: Porto Seguro FIRF | Y1: Porto Seguro Ipê | Z1: Sparta Max Advisory | AA1: Sparta Top Advisory
A2: ARX Denali | B2: =Correlação!C2 -> 1 | C2: =Correlação!D2 -> 0.80660057 | D2: =Correlação!E2 -> 0.86557442 | E2: =Correlação!F2 -> 0.30936013 | F2: =Correlação!G2 -> 0.11717329 | G2: =Correlação!H2 -> 0.17470048 | H2: =Correlação!I2 -> 0.1226426 | I2: =Correlação!J2 -> 0.051435473 | ... AA2: =Correlação!AB2 -> 0.070134819
A3: ARX Everest Advisory | B3: =Correlação!C3 -> 0.80660057 | C3: =Correlação!D3 -> 1 | D3: =Correlação!E3 -> 0.91799651 | E3: =Correlação!F3 -> 0.24077845 | F3: =Correlação!G3 -> 0.033221823 | G3: =Correlação!H3 -> 0.057506898 | H3: =Correlação!I3 -> -0.046931959 | I3: =Correlação!J3 -> 0.0065493193 | ... AA3: =Correlação!AB3 -> 0.09451381
A4: ARX Vinson Advisory | B4: =Correlação!C4 -> 0.86557442 | C4: =Correlação!D4 -> 0.91799651 | D4: =Correlação!E4 -> 1 | E4: =Correlação!F4 -> 0.22598785 | F4: =Correlação!G4 -> 0.087303385 | G4: =Correlação!H4 -> 0.13279623 | H4: =Correlação!I4 -> 0.031033905 | I4: =Correlação!J4 -> 0.055816487 | ... AA4: =Correlação!AB4 -> 0.12203094
A5: Capitânia Top | B5: =Correlação!C5 -> 0.30936013 | C5: =Correlação!D5 -> 0.24077845 | D5: =Correlação!E5 -> 0.22598785 | E5: =Correlação!F5 -> 1 | F5: =Correlação!G5 -> -0.0038735133 | G5: =Correlação!H5 -> -0.00088875867 | H5: =Correlação!I5 -> 0.007610546 | I5: =Correlação!J5 -> 0.23137622 | ... AA5: =Correlação!AB5 -> 0.045666972
A6: Absolute Atenas | B6: =Correlação!C6 -> 0.11717329 | C6: =Correlação!D6 -> 0.033221823 | D6: =Correlação!E6 -> 0.087303385 | E6: =Correlação!F6 -> -0.0038735133 | F6: =Correlação!G6 -> 1 | G6: =Correlação!H6 -> 0.94246151 | H6: =Correlação!I6 -> 0.59634361 | I6: =Correlação!J6 -> 0.077544848 | ... AA6: =Correlação!AB6 -> 0.16134596
A7: Absolute Creta | B7: =Correlação!C7 -> 0.17470048 | C7: =Correlação!D7 -> 0.057506898 | D7: =Correlação!E7 -> 0.13279623 | E7: =Correlação!F7 -> -0.00088875867 | F7: =Correlação!G7 -> 0.94246151 | G7: =Correlação!H7 -> 1 | H7: =Correlação!I7 -> 0.65863419 | I7: =Correlação!J7 -> 0.086211791 | ... AA7: =Correlação!AB7 -> 0.20076021
A8: Absolute Olimpia | B8: =Correlação!C8 -> 0.1226426 | C8: =Correlação!D8 -> -0.046931959 | D8: =Correlação!E8 -> 0.031033905 | E8: =Correlação!F8 -> 0.007610546 | F8: =Correlação!G8 -> 0.59634361 | G8: =Correlação!H8 -> 0.65863419 | H8: =Correlação!I8 -> 1 | I8: =Correlação!J8 -> 0.11890789 | ... AA8: =Correlação!AB8 -> 0.1534743
A9: Horizonte | B9: =Correlação!C9 -> 0.051435473 | C9: =Correlação!D9 -> 0.0065493193 | D9: =Correlação!E9 -> 0.055816487 | E9: =Correlação!F9 -> 0.23137622 | F9: =Correlação!G9 -> 0.077544848 | G9: =Correlação!H9 -> 0.086211791 | H9: =Correlação!I9 -> 0.11890789 | I9: =Correlação!J9 -> 1 | ... AA9: =Correlação!AB9 -> 0.18780982
A10: Geraes 30 | B10: =Correlação!C10 -> 0.083672675 | C10: =Correlação!D10 -> 0.050991617 | D10: =Correlação!E10 -> 0.094052928 | E10: =Correlação!F10 -> 0.15293293 | F10: =Correlação!G10 -> 0.046949027 | G10: =Correlação!H10 -> 0.050288899 | H10: =Correlação!I10 -> 0.059485705 | I10: =Correlação!J10 -> 0.6866213 | ... AA10: =Correlação!AB10 -> 0.2554295
A11: GERAES | B11: =Correlação!C11 -> 0.083464113 | C11: =Correlação!D11 -> 0.028904916 | D11: =Correlação!E11 -> 0.077938592 | E11: =Correlação!F11 -> 0.23417922 | F11: =Correlação!G11 -> 0.063685688 | G11: =Correlação!H11 -> 0.070308478 | H11: =Correlação!I11 -> 0.088274223 | I11: =Correlação!J11 -> 0.77396937 | ... AA11: =Correlação!AB11 -> 0.25207875
A12: Riza Lotus | B12: =Correlação!C12 -> 0.075141071 | C12: =Correlação!D12 -> -0.0053501093 | D12: =Correlação!E12 -> 0.056631131 | E12: =Correlação!F12 -> 0.038473756 | F12: =Correlação!G12 -> 0.041976162 | G12: =Correlação!H12 -> 0.10417812 | H12: =Correlação!I12 -> 0.17465304 | I12: =Correlação!J12 -> 0.090689796 | ... AA12: =Correlação!AB12 -> 0.17452378
A13: Riza Lotus Plus | B13: =Correlação!C13 -> 0.022642024 | C13: =Correlação!D13 -> -0.034782462 | D13: =Correlação!E13 -> 0.013461238 | E13: =Correlação!F13 -> 0.065765607 | F13: =Correlação!G13 -> 0.015833454 | G13: =Correlação!H13 -> 0.053055291 | H13: =Correlação!I13 -> 0.12239907 | I13: =Correlação!J13 -> 0.071674814 | ... AA13: =Correlação!AB13 -> 0.11686734
... A27: Sparta Top Advisory | B27: =Correlação!C27 -> 0.070134819 | C27: =Correlação!D27 -> 0.09451381 | D27: =Correlação!E27 -> 0.12203094 | E27: =Correlação!F27 -> 0.045666972 | F27: =Correlação!G27 -> 0.16134596 | G27: =Correlação!H27 -> 0.20076021 | H27: =Correlação!I27 -> 0.1534743 | I27: =Correlação!J27 -> 0.18780982 | ... AA27: =Correlação!AB27 -> 1
